[{"c":"e","n":"おがみ山","a":"鹿児島県奄美市名瀬永田町14","la":28.374256,"lo":129.495786},{"c":"e","n":"しんまち公園","a":"鹿児島県奄美市名瀬朝仁新町37","la":28.394398,"lo":129.486775},{"c":"e","n":"すこやか福祉センター","a":"鹿児島県瀬戸内町古仁屋船津23","la":28.146309,"lo":129.314904},{"c":"e","n":"ながはま公園","a":"鹿児島県奄美市名瀬長浜町30","la":28.397934,"lo":129.492712},{"c":"e","n":"らんかん山","a":"鹿児島県奄美市名瀬矢之脇町7","la":28.382253,"lo":129.491276},{"c":"e","n":"エコーＡＭＡＭＩ","a":"鹿児島県奄美市名瀬大字小宿291","la":28.399412,"lo":129.464012},{"c":"e","n":"グランセ末広ビル","a":"鹿児島県奄美市名瀬末広町18-25","la":28.377161,"lo":129.494474},{"c":"e","n":"ゼログラヴィティ","a":"鹿児島県瀬戸内町清水122","la":28.135807,"lo":129.328142},{"c":"e","n":"ホテルウエストコート奄美","a":"鹿児島県奄美市名瀬入舟町9-1","la":28.381589,"lo":129.493112},{"c":"e","n":"ホテルビッグマリン奄美","a":"鹿児島県奄美市名瀬長浜町27-1","la":28.396556,"lo":129.49533},{"c":"e","n":"三浦集会所","a":"鹿児島県瀬戸内町三浦10","la":28.149744,"lo":129.245131},{"c":"e","n":"上原農道","a":"鹿児島県奄美市名瀬朝仁新町5","la":28.400732,"lo":129.483913},{"c":"e","n":"上役勝集落墓地前","a":"鹿児島県奄美市住用町役勝296-25","la":28.234177,"lo":129.372439},{"c":"e","n":"与路小・中学校グランド","a":"鹿児島県瀬戸内町与路484","la":28.044597,"lo":129.163344},{"c":"e","n":"与路小・中学校体育館","a":"鹿児島県瀬戸内町与路484","la":28.044602,"lo":129.163649},{"c":"e","n":"与路離島住民生活センター","a":"鹿児島県瀬戸内町与路383","la":28.044443,"lo":129.164091},{"c":"e","n":"中役勝公民館裏山","a":"鹿児島県奄美市住用町役勝192","la":28.252,"lo":129.380505},{"c":"e","n":"丸親ビル","a":"鹿児島県奄美市名瀬港町9-7","la":28.380703,"lo":129.495974},{"c":"e","n":"久志小中学校","a":"鹿児島県宇検村久志2","la":28.286723,"lo":129.233159},{"c":"e","n":"久志小中学校体育館","a":"鹿児島県宇検村久志2","la":28.287101,"lo":129.233325},{"c":"e","n":"久慈小・中学校グランド","a":"鹿児島県瀬戸内町久慈253","la":28.232955,"lo":129.253003},{"c":"e","n":"久慈小・中学校体育館","a":"鹿児島県瀬戸内町久慈253","la":28.233082,"lo":129.253389},{"c":"e","n":"久慈集会所","a":"鹿児島県瀬戸内町久慈783","la":28.229604,"lo":129.251662},{"c":"e","n":"久根津集会所","a":"鹿児島県瀬戸内町久根津413","la":28.169945,"lo":129.297726},{"c":"e","n":"今里公民館","a":"鹿児島県大和村今里498","la":28.325341,"lo":129.27509},{"c":"e","n":"今里小学校","a":"鹿児島県大和村今里３６１－イ","la":28.326209,"lo":129.278678},{"c":"e","n":"介護老人保健施設　虹の丘","a":"鹿児島県奄美市名瀬大字小宿3416-1","la":28.385872,"lo":129.474676},{"c":"e","n":"介護老人保健施設せとうち","a":"鹿児島県瀬戸内町阿木名1975","la":28.170397,"lo":129.335833},{"c":"e","n":"伊子茂小・中学校グランド","a":"鹿児島県瀬戸内町伊子茂207","la":28.107867,"lo":129.243348},{"c":"e","n":"伊子茂小・中学校体育館","a":"鹿児島県瀬戸内町伊子茂207","la":28.107479,"lo":129.243708},{"c":"e","n":"伊須集会所","a":"鹿児島県瀬戸内町伊須402-2","la":28.150058,"lo":129.355834},{"c":"e","n":"住用中学校裏山","a":"鹿児島県奄美市住用町役勝27","la":28.255587,"lo":129.399485},{"c":"e","n":"佐念公民館","a":"鹿児島県宇検村佐念134","la":28.263074,"lo":129.236845},{"c":"e","n":"佐知克林業研修集会施設","a":"鹿児島県瀬戸内町於斉佐知克1844","la":28.088764,"lo":129.26648},{"c":"e","n":"俵コミュニティーセンター","a":"鹿児島県瀬戸内町俵23","la":28.135999,"lo":129.241515},{"c":"e","n":"俵中学校グランド","a":"鹿児島県瀬戸内町俵1126","la":28.134854,"lo":129.240045},{"c":"e","n":"俵中学校体育館","a":"鹿児島県瀬戸内町俵126","la":28.135637,"lo":129.239173},{"c":"e","n":"加計呂麻園","a":"鹿児島県瀬戸内町伊子茂187-1","la":28.108443,"lo":129.243693},{"c":"e","n":"加計呂麻島展示　体験交流館","a":"鹿児島県瀬戸内町諸鈍316","la":28.093541,"lo":129.325463},{"c":"e","n":"勝浦集会所","a":"鹿児島県瀬戸内町勝浦1446-1","la":28.174954,"lo":129.3468},{"c":"e","n":"勝能離島住民生活センター","a":"鹿児島県瀬戸内町勝能887-2","la":28.107356,"lo":129.295327},{"c":"e","n":"南海団地：朝仁町９番地内","a":"鹿児島県奄美市名瀬朝仁町9","la":28.39714,"lo":129.481376},{"c":"e","n":"去勝地区農道横","a":"鹿児島県奄美市住用町役勝去勝117","la":28.255642,"lo":129.387685},{"c":"e","n":"古仁屋中学校グランド","a":"鹿児島県瀬戸内町古仁屋842-8","la":28.149867,"lo":129.315746},{"c":"e","n":"古仁屋中学校体育館","a":"鹿児島県瀬戸内町古仁屋842-8","la":28.150282,"lo":129.316401},{"c":"e","n":"古仁屋小学校グランド","a":"鹿児島県瀬戸内町古仁屋805","la":28.149943,"lo":129.314132},{"c":"e","n":"古仁屋小学校体育館","a":"鹿児島県瀬戸内町古仁屋805","la":28.149568,"lo":129.314169},{"c":"e","n":"古仁屋漁港ターミナルビル","a":"鹿児島県瀬戸内町古仁屋大湊26-14","la":28.145297,"lo":129.308982},{"c":"e","n":"古仁屋高等学校グランド","a":"鹿児島県瀬戸内町古仁屋399-1","la":28.152047,"lo":129.31256},{"c":"e","n":"古仁屋高等学校体育館","a":"鹿児島県瀬戸内町古仁屋399-1","la":28.151978,"lo":129.312072},{"c":"e","n":"古志集会所","a":"鹿児島県瀬戸内町古志緑1039","la":28.233233,"lo":129.276729},{"c":"e","n":"名柄小中学校","a":"鹿児島県宇検村名柄1263","la":28.252203,"lo":129.24998},{"c":"e","n":"名柄小中学校体育館","a":"鹿児島県宇検村名柄1263","la":28.252629,"lo":129.249304},{"c":"e","n":"名瀬・瀬戸内線（国直方面）","a":"鹿児島県奄美市名瀬知名瀬","la":28.3843,"lo":129.430592},{"c":"e","n":"名瀬中学校（校舎）","a":"鹿児島県奄美市名瀬真名津町14-1","la":28.364542,"lo":129.498842},{"c":"e","n":"名瀬小学校（校舎）","a":"鹿児島県奄美市名瀬永田町1-1","la":28.376294,"lo":129.493195},{"c":"e","n":"名音小学校","a":"鹿児島県大和村名音６０３－イ","la":28.334582,"lo":129.315586},{"c":"e","n":"名音生活館","a":"鹿児島県大和村名音368","la":28.335679,"lo":129.314015},{"c":"e","n":"嘉入離島住民生活センター","a":"鹿児島県瀬戸内町嘉入288","la":28.141507,"lo":129.218777},{"c":"e","n":"嘉徳集会所","a":"鹿児島県瀬戸内町嘉徳422","la":28.193453,"lo":129.403769},{"c":"e","n":"嘉鉄小学校グランド","a":"鹿児島県瀬戸内町嘉鉄353","la":28.139033,"lo":129.343385},{"c":"e","n":"嘉鉄小学校体育館","a":"鹿児島県瀬戸内町嘉鉄353","la":28.138743,"lo":129.343986},{"c":"e","n":"嘉鉄集会所","a":"鹿児島県瀬戸内町嘉鉄322-2","la":28.138662,"lo":129.343266},{"c":"e","n":"国直公民館","a":"鹿児島県大和村国直106-2","la":28.371952,"lo":129.407018},{"c":"e","n":"塩浜町１５番地内","a":"鹿児島県奄美市名瀬塩浜町15","la":28.38917,"lo":129.492423},{"c":"e","n":"大和中学校","a":"鹿児島県大和村思勝370","la":28.355704,"lo":129.39522},{"c":"e","n":"大和小学校","a":"鹿児島県大和村思勝370","la":28.355468,"lo":129.395494},{"c":"e","n":"大和小学校湯湾釜分校","a":"鹿児島県大和村湯湾釜184","la":28.364483,"lo":129.411999},{"c":"e","n":"大和村体育館","a":"鹿児島県大和村思勝485","la":28.356839,"lo":129.393506},{"c":"e","n":"大和村老人福祉センター","a":"鹿児島県大和村戸円1882-3","la":28.346846,"lo":129.315897},{"c":"e","n":"大和村防災センター","a":"鹿児島県大和村思勝477-1","la":28.356985,"lo":129.394053},{"c":"e","n":"大和浜公民館","a":"鹿児島県大和村大和浜17-29","la":28.35904,"lo":129.397209},{"c":"e","n":"大島郡医師会病院","a":"鹿児島県奄美市名瀬大字小宿3411","la":28.386444,"lo":129.474393},{"c":"e","n":"大棚公民館","a":"鹿児島県大和村大棚108-11","la":28.357224,"lo":129.359612},{"c":"e","n":"大棚小学校","a":"鹿児島県大和村大棚78-1","la":28.355833,"lo":129.359368},{"c":"e","n":"大金久防災会館","a":"鹿児島県大和村大金久312-1","la":28.361291,"lo":129.350747},{"c":"e","n":"奄美の園","a":"鹿児島県瀬戸内町古仁屋1283-27","la":28.13847,"lo":129.320685},{"c":"e","n":"奄美サンプラザホテル","a":"鹿児島県奄美市名瀬港町2-1","la":28.381088,"lo":129.494888},{"c":"e","n":"奄美フォレストポリス","a":"鹿児島県大和村名音1476","la":28.315821,"lo":129.335958},{"c":"e","n":"奄美ポートタワーホテル","a":"鹿児島県奄美市名瀬塩浜町4-12","la":28.386304,"lo":129.49377},{"c":"e","n":"奄美中央病院","a":"鹿児島県奄美市名瀬長浜町16-5","la":28.394462,"lo":129.493478},{"c":"e","n":"奄美小学校（校舎）","a":"鹿児島県奄美市名瀬久里町15-10","la":28.372876,"lo":129.497359},{"c":"e","n":"奄美市老人福祉会館","a":"鹿児島県奄美市名瀬長浜町2394","la":28.39835,"lo":129.493077},{"c":"e","n":"奄美市ＡｉＡｉひろば","a":"鹿児島県奄美市名瀬末広町14-10","la":28.377458,"lo":129.495928},{"c":"e","n":"奄美高校（校舎）","a":"鹿児島県奄美市名瀬古田町1-1","la":28.371654,"lo":129.497992},{"c":"e","n":"宇検村地域福祉センター","a":"鹿児島県宇検村湯湾2937-87","la":28.274235,"lo":129.295701},{"c":"e","n":"宇検村総合体育館","a":"鹿児島県宇検村湯湾2943","la":28.276139,"lo":129.298374},{"c":"e","n":"宇検診療所","a":"鹿児島県宇検村湯湾37","la":28.279059,"lo":129.294952},{"c":"e","n":"安脚場集会所","a":"鹿児島県瀬戸内町渡連890","la":28.10751,"lo":129.345909},{"c":"e","n":"実久集会所","a":"鹿児島県瀬戸内町実久179-2","la":28.185952,"lo":129.18546},{"c":"e","n":"寿老園","a":"鹿児島県瀬戸内町古仁屋瀬久井西7-3","la":28.144613,"lo":129.319972},{"c":"e","n":"小名瀬林業研修館","a":"鹿児島県瀬戸内町小名瀬122","la":28.196209,"lo":129.280714},{"c":"e","n":"小宿中学校（校舎）","a":"鹿児島県奄美市名瀬大字小宿2788","la":28.394632,"lo":129.46746},{"c":"e","n":"小宿厳島神社","a":"鹿児島県奄美市名瀬大字小宿","la":28.393327,"lo":129.464834},{"c":"e","n":"小宿小学校（校舎）","a":"鹿児島県奄美市名瀬大字小宿900","la":28.394584,"lo":129.464783},{"c":"e","n":"山間集落高千穂神社","a":"鹿児島県奄美市住用町大字山間135","la":28.241823,"lo":129.414377},{"c":"e","n":"川内集落裏畑","a":"鹿児島県奄美市住用町川内82","la":28.306693,"lo":129.432297},{"c":"e","n":"市小中学校裏畑","a":"鹿児島県奄美市住用町市中里62","la":28.227589,"lo":129.454144},{"c":"e","n":"市道三太郎線","a":"鹿児島県奄美市住用町石原立篭15","la":28.264489,"lo":129.41041},{"c":"e","n":"市道三太郎線","a":"鹿児島県奄美市住用町東仲間桂勝山1028","la":28.289857,"lo":129.434057},{"c":"e","n":"市道和瀬城線","a":"鹿児島県奄美市住用町城小和瀬1306","la":28.298248,"lo":129.465266},{"c":"e","n":"市道塩浜朝に線（赤崎方向）","a":"鹿児島県奄美市名瀬長浜町3","la":28.390392,"lo":129.493431},{"c":"e","n":"市道大塔線","a":"鹿児島県奄美市住用町見里チャ水958","la":28.283862,"lo":129.44161},{"c":"e","n":"市道山間市線","a":"鹿児島県奄美市住用町山間持寄470-1","la":28.231992,"lo":129.430817},{"c":"e","n":"市道平田・朝戸線","a":"鹿児島県奄美市名瀬大字朝戸９８７先","la":28.33752,"lo":129.495716},{"c":"e","n":"市道平田・朝戸線","a":"鹿児島県奄美市名瀬平田町２１先","la":28.358899,"lo":129.498467},{"c":"e","n":"市道朝戸・和瀬線","a":"鹿児島県奄美市名瀬大字朝戸","la":28.329415,"lo":129.495399},{"c":"e","n":"市道里～福里間市道","a":"鹿児島県奄美市名瀬大字小宿2581-1","la":28.38768,"lo":129.467865},{"c":"e","n":"市道青久線","a":"鹿児島県奄美市住用町市青久1722","la":28.201406,"lo":129.438025},{"c":"e","n":"平田公民館","a":"鹿児島県宇検村平田59","la":28.253807,"lo":129.20469},{"c":"e","n":"平田町２２番地内（市道平田２９号線）","a":"鹿児島県奄美市名瀬平田町22","la":28.358295,"lo":129.499597},{"c":"e","n":"役場庁舎会議室","a":"鹿児島県宇検村湯湾915","la":28.280716,"lo":129.297278},{"c":"e","n":"徳浜離島住民生活センター","a":"鹿児島県瀬戸内町徳浜1170","la":28.074249,"lo":129.328587},{"c":"e","n":"志戸勘公民館","a":"鹿児島県大和村志戸勘398-3","la":28.327088,"lo":129.290627},{"c":"e","n":"思勝コミュニティセンター","a":"鹿児島県大和村思勝363-3","la":28.35505,"lo":129.395167},{"c":"e","n":"慈愛会奄美病院","a":"鹿児島県奄美市名瀬浜里町170","la":28.397043,"lo":129.472257},{"c":"e","n":"戸円公民館","a":"鹿児島県大和村戸円452-2","la":28.350706,"lo":129.329808},{"c":"e","n":"手安集会所","a":"鹿児島県瀬戸内町手安153","la":28.160946,"lo":129.297425},{"c":"e","n":"押角集会所","a":"鹿児島県瀬戸内町押角456-5","la":28.113056,"lo":129.272969},{"c":"e","n":"新和瀬トンネル前広場","a":"鹿児島県奄美市住用町和瀬山地660","la":28.300426,"lo":129.477947},{"c":"e","n":"於斉高齢者コミュニティーセンター","a":"鹿児島県瀬戸内町於斉205","la":28.112424,"lo":129.249625},{"c":"e","n":"旧和瀬浄水場","a":"鹿児島県奄美市住用町和瀬仲山５５７－甲","la":28.295455,"lo":129.476309},{"c":"e","n":"旧役勝浄水場","a":"鹿児島県奄美市住用町役勝池畑259-12","la":28.243697,"lo":129.372935},{"c":"e","n":"旧花天分校","a":"鹿児島県瀬戸内町花天120","la":28.22956,"lo":129.216625},{"c":"e","n":"木慈集会所","a":"鹿児島県瀬戸内町木慈113","la":28.158565,"lo":129.220097},{"c":"e","n":"東団地：朝仁新町４３・４５・４６・４７番地内","a":"鹿児島県奄美市名瀬朝仁新町43","la":28.391604,"lo":129.486138},{"c":"e","n":"東城小中学校裏山","a":"鹿児島県奄美市住用町摺勝610","la":28.294984,"lo":129.443378},{"c":"e","n":"林道住用中央東線","a":"鹿児島県奄美市住用町市白畑1072","la":28.220692,"lo":129.448144},{"c":"e","n":"林道城線","a":"鹿児島県奄美市住用町城池田34-1","la":28.297621,"lo":129.45849},{"c":"e","n":"林道山間支線","a":"鹿児島県奄美市住用町山間戸玉５４８－ロ","la":28.234079,"lo":129.426898},{"c":"e","n":"林道滝行線","a":"鹿児島県奄美市住用町山間カズラ勝821","la":28.24598,"lo":129.408105},{"c":"e","n":"柳町１７・１９番地内（通称：腰又）","a":"鹿児島県奄美市柳町17","la":28.380184,"lo":129.488465},{"c":"e","n":"森田邸裏山","a":"鹿児島県奄美市住用町摺勝736","la":28.297283,"lo":129.441642},{"c":"e","n":"武名離島住民生活センター","a":"鹿児島県瀬戸内町武名39","la":28.153453,"lo":129.232848},{"c":"e","n":"水源地","a":"鹿児島県奄美市名瀬根瀬部","la":28.379906,"lo":129.432766},{"c":"e","n":"池地小学校グランド","a":"鹿児島県瀬戸内町池地329","la":28.030056,"lo":129.238658},{"c":"e","n":"池地小学校体育館","a":"鹿児島県瀬戸内町池地329","la":28.030108,"lo":129.238192},{"c":"e","n":"池地集会所","a":"鹿児島県瀬戸内町池地638","la":28.030729,"lo":129.232479},{"c":"e","n":"油井小・中学校グランド","a":"鹿児島県瀬戸内町油井603-1","la":28.181732,"lo":129.293776},{"c":"e","n":"油井小・中学校体育館","a":"鹿児島県瀬戸内町油井603-1","la":28.182304,"lo":129.293379},{"c":"e","n":"油井集会所","a":"鹿児島県瀬戸内町油井602","la":28.182492,"lo":129.292964},{"c":"e","n":"津名久防災会館","a":"鹿児島県大和村津名久65-1","la":28.355284,"lo":129.400753},{"c":"e","n":"清水公園","a":"鹿児島県瀬戸内町清水３９２","la":28.141169,"lo":129.33017},{"c":"e","n":"清水公園総合　体育館","a":"鹿児島県瀬戸内町清水392","la":28.141119,"lo":129.328547},{"c":"e","n":"清水公園総合陸上競技場","a":"鹿児島県瀬戸内町清水392","la":28.14003,"lo":129.327115},{"c":"e","n":"清水集会所","a":"鹿児島県瀬戸内町清水137","la":28.135919,"lo":129.328886},{"c":"e","n":"渡連集会所","a":"鹿児島県瀬戸内町渡連227","la":28.111702,"lo":129.339579},{"c":"e","n":"湯湾会館","a":"鹿児島県宇検村湯湾712-9","la":28.278815,"lo":129.296214},{"c":"e","n":"湯湾生活館","a":"鹿児島県宇検村湯湾722","la":28.279965,"lo":129.295939},{"c":"e","n":"湯湾釜公民館","a":"鹿児島県大和村湯湾釜213","la":28.364233,"lo":129.41215},{"c":"e","n":"瀬久井集会所","a":"鹿児島県瀬戸内町古仁屋瀬久井西15-1","la":28.143761,"lo":129.318334},{"c":"e","n":"瀬戸内町きゅら島交流館","a":"鹿児島県瀬戸内町古仁屋船津33","la":28.145782,"lo":129.315245},{"c":"e","n":"瀬戸内町役場庁舎","a":"鹿児島県瀬戸内町古仁屋船津23","la":28.146519,"lo":129.314666},{"c":"e","n":"瀬武集会所","a":"鹿児島県瀬戸内町瀬武115","la":28.165899,"lo":129.209962},{"c":"e","n":"瀬相集会所","a":"鹿児島県瀬戸内町瀬相92-1","la":28.12289,"lo":129.244651},{"c":"e","n":"生勝公民館","a":"鹿児島県宇検村生勝181-2","la":28.285411,"lo":129.24348},{"c":"e","n":"生間林業研修館","a":"鹿児島県瀬戸内町生間167-1","la":28.105419,"lo":129.325362},{"c":"e","n":"田検中学校","a":"鹿児島県宇検村田検191","la":28.285865,"lo":129.290067},{"c":"e","n":"田検中学校体育館","a":"鹿児島県宇検村田検191","la":28.285646,"lo":129.290834},{"c":"e","n":"田検保育所","a":"鹿児島県宇検村田検102-3","la":28.284725,"lo":129.290471},{"c":"e","n":"田検小学校","a":"鹿児島県宇検村田検37","la":28.285324,"lo":129.292894},{"c":"e","n":"町営キャンプ場施設西古見ＧＡＴＥ","a":"鹿児島県瀬戸内町西古見265","la":28.242911,"lo":129.175229},{"c":"e","n":"真名津町１１番地内","a":"鹿児島県奄美市名瀬真名津町11","la":28.363205,"lo":129.496119},{"c":"e","n":"矢之脇町１４・１５番地内","a":"鹿児島県奄美市名瀬矢之脇町14","la":28.38386,"lo":129.490076},{"c":"e","n":"知之浦集会所","a":"鹿児島県瀬戸内町武名前田原579","la":28.163232,"lo":129.263366},{"c":"e","n":"石良公民館","a":"鹿児島県宇検村湯湾1640-8","la":28.269981,"lo":129.311712},{"c":"e","n":"神社（根瀬部）","a":"鹿児島県奄美市名瀬根瀬部866","la":28.381546,"lo":129.43167},{"c":"e","n":"神社（知名瀬）","a":"鹿児島県奄美市名瀬知名瀬2217","la":28.377671,"lo":129.451046},{"c":"e","n":"秋徳小・中学校グランド","a":"鹿児島県瀬戸内町秋徳245","la":28.085368,"lo":129.283036},{"c":"e","n":"秋徳小・中学校体育館","a":"鹿児島県瀬戸内町秋徳245","la":28.085576,"lo":129.282403},{"c":"e","n":"秋徳小中学校","a":"鹿児島県瀬戸内町秋徳245","la":28.085425,"lo":129.282833},{"c":"e","n":"秋徳離島住民生活センター","a":"鹿児島県瀬戸内町秋徳96-1","la":28.083954,"lo":129.284158},{"c":"e","n":"第３里見ビル","a":"鹿児島県奄美市名瀬矢之脇町10-5","la":28.383772,"lo":129.492472},{"c":"e","n":"管鈍集会所","a":"鹿児島県瀬戸内町管鈍149-1","la":28.228112,"lo":129.194272},{"c":"e","n":"節子集会所","a":"鹿児島県瀬戸内町節子1201","la":28.166478,"lo":129.380265},{"c":"e","n":"篠川地区振興センター","a":"鹿児島県瀬戸内町篠川567-1","la":28.222393,"lo":129.294798},{"c":"e","n":"篠川小・中学校グランド","a":"鹿児島県瀬戸内町篠川150","la":28.222472,"lo":129.298173},{"c":"e","n":"篠川小・中学校体育館","a":"鹿児島県瀬戸内町篠川150","la":28.222293,"lo":129.298552},{"c":"e","n":"網野子集会所","a":"鹿児島県瀬戸内町網野子189","la":28.169579,"lo":129.36227},{"c":"e","n":"芝集会所","a":"鹿児島県瀬戸内町芝219","la":28.192445,"lo":129.210342},{"c":"e","n":"芦検公民館","a":"鹿児島県宇検村芦検517-3","la":28.287175,"lo":129.269346},{"c":"e","n":"花富集会所","a":"鹿児島県瀬戸内町花富117","la":28.100102,"lo":129.239451},{"c":"e","n":"薩川中学校グランド","a":"鹿児島県瀬戸内町薩川767","la":28.17895,"lo":129.204032},{"c":"e","n":"薩川中学校体育館","a":"鹿児島県瀬戸内町薩川767","la":28.178638,"lo":129.204444},{"c":"e","n":"薩川小学校グランド","a":"鹿児島県瀬戸内町薩川211","la":28.180403,"lo":129.202858},{"c":"e","n":"薩川小学校講堂","a":"鹿児島県瀬戸内町薩川211","la":28.180115,"lo":129.202729},{"c":"e","n":"薩川集会所","a":"鹿児島県瀬戸内町薩川189","la":28.180469,"lo":129.202257},{"c":"e","n":"蘇刈集会所","a":"鹿児島県瀬戸内町蘇刈447","la":28.135818,"lo":129.359949},{"c":"e","n":"西古見防災コミュニティセンター","a":"鹿児島県瀬戸内町西古見603-1","la":28.240876,"lo":129.171415},{"c":"e","n":"西阿室小学校","a":"鹿児島県瀬戸内町西阿室135","la":28.111738,"lo":129.222101},{"c":"e","n":"西阿室小学校グランド","a":"鹿児島県瀬戸内町西阿室135","la":28.111535,"lo":129.222085},{"c":"e","n":"西阿室小学校体育館","a":"鹿児島県瀬戸内町西阿室135","la":28.111559,"lo":129.222299},{"c":"e","n":"西阿室離島住民生活センター","a":"鹿児島県瀬戸内町西阿室146-5","la":28.111275,"lo":129.22238},{"c":"e","n":"請阿室集会所","a":"鹿児島県瀬戸内町請阿室401-1","la":28.028547,"lo":129.254162},{"c":"e","n":"諸数集会所","a":"鹿児島県瀬戸内町諸数252-1","la":28.107926,"lo":129.314491},{"c":"e","n":"諸鈍小・中学校グランド","a":"鹿児島県瀬戸内町諸鈍２９５－イ","la":28.094597,"lo":129.325601},{"c":"e","n":"諸鈍小・中学校体育館","a":"鹿児島県瀬戸内町諸鈍２９５－イ","la":28.094596,"lo":129.326098},{"c":"e","n":"諸鈍離島住民生活センター","a":"鹿児島県瀬戸内町諸鈍371","la":28.091454,"lo":129.326103},{"c":"e","n":"赤崎公園・千年松方面市道","a":"鹿児島県奄美市名瀬大字朝仁847","la":28.398196,"lo":129.486136},{"c":"e","n":"部連公民館","a":"鹿児島県宇検村部連622-7","la":28.260905,"lo":129.273676},{"c":"e","n":"配田が丘","a":"鹿児島県奄美市名瀬久里町15-10","la":28.372294,"lo":129.496943},{"c":"e","n":"野見山青少年研修センター","a":"鹿児島県瀬戸内町野見山361","la":28.094189,"lo":129.29123},{"c":"e","n":"金久中学校（校舎）","a":"鹿児島県奄美市名瀬塩浜町15-10","la":28.388423,"lo":129.492875},{"c":"e","n":"長浜町１６番地内（にっしょう団地）","a":"鹿児島県奄美市名瀬長浜町16","la":28.394243,"lo":129.492843},{"c":"e","n":"阿多地集会所","a":"鹿児島県瀬戸内町阿多地96","la":28.152098,"lo":129.1987},{"c":"e","n":"阿室小中学校","a":"鹿児島県宇検村阿室195","la":28.256631,"lo":129.200229},{"c":"e","n":"阿室小中学校体育館","a":"鹿児島県宇検村阿室195","la":28.25648,"lo":129.199392},{"c":"e","n":"阿室釜林業研修館","a":"鹿児島県瀬戸内町阿室釜4-13","la":28.220525,"lo":129.294727},{"c":"e","n":"阿木名小・中学校グランド","a":"鹿児島県瀬戸内町阿木名2141","la":28.17049,"lo":129.337113},{"c":"e","n":"阿木名小・中学校体育館","a":"鹿児島県瀬戸内町阿木名2141","la":28.17074,"lo":129.337676},{"c":"e","n":"阿木名集会所","a":"鹿児島県瀬戸内町阿木名17","la":28.167,"lo":129.334104},{"c":"e","n":"阿鉄集会所","a":"鹿児島県瀬戸内町阿鉄725","la":28.189575,"lo":129.290604},{"c":"e","n":"須古公民館","a":"鹿児島県宇検村須古472-5","la":28.272245,"lo":129.293942},{"c":"e","n":"須子茂集会所","a":"鹿児島県瀬戸内町須子茂62","la":28.146254,"lo":129.210956},{"c":"e","n":"須手集会所","a":"鹿児島県瀬戸内町手安785-5","la":28.151145,"lo":129.300329},{"c":"e","n":"高丘集会所","a":"鹿児島県瀬戸内町古仁屋233-3","la":28.155324,"lo":129.31301},{"c":"e","n":"高千穂神社","a":"鹿児島県奄美市名瀬井根町19-1","la":28.375247,"lo":129.490291},{"c":"e","n":"高齢者避難所","a":"鹿児島県大和村戸円452-1","la":28.350716,"lo":129.329728},{"c":"f","n":"大島地区消防組合名瀬消防署住用消防分駐所","a":"","la":28.254587,"lo":129.397989},{"c":"f","n":"大島地区消防組合名瀬消防署大和消防分駐所","a":"","la":28.357157,"lo":129.394513},{"c":"f","n":"大島地区消防組合名瀬消防署宇検消防分駐所","a":"","la":28.275534,"lo":129.29664},{"c":"f","n":"大島地区消防組合名瀬消防署瀬戸内消防分署","a":"","la":28.137326,"lo":129.320125},{"c":"f","n":"大島地区消防組合名瀬消防署瀬戸内消防分署加計呂麻消防分駐所","a":"","la":28.121693,"lo":129.246033},{"c":"m","n":"いい・かねゆきクリニック","a":"奄美市名瀬長浜町４－１１","la":28.390942,"lo":129.494492},{"c":"m","n":"いづはら医院","a":"大島郡瀬戸内町古仁屋大湊７","la":28.147205,"lo":129.310221},{"c":"m","n":"うえだクリニック","a":"奄美市名瀬真名津町１３－２０","la":28.36335,"lo":129.499879},{"c":"m","n":"かずや内科","a":"奄美市名瀬平松町５３２","la":28.39888,"lo":129.467368},{"c":"m","n":"くばら歯科医院","a":"奄美市名瀬古田町１６-１","la":28.369866,"lo":129.499105},{"c":"m","n":"ささはらメンタルクリニック","a":"奄美市名瀬伊津部町１６－７","la":28.378109,"lo":129.498724},{"c":"m","n":"せき歯科医院","a":"大島郡瀬戸内町古仁屋春日４－４","la":28.147437,"lo":129.311123},{"c":"m","n":"つばたクリニック","a":"奄美市名瀬久里町９－２","la":28.375239,"lo":129.49744},{"c":"m","n":"つばた歯科クリニック","a":"奄美市名瀬久里町9-6","la":28.375046,"lo":129.497426},{"c":"m","n":"なのはな園診療所","a":"大島郡瀬戸内町勝能８８７","la":28.107203,"lo":129.29527},{"c":"m","n":"まちだ歯科","a":"大島郡瀬戸内町古仁屋１０５２－１","la":28.145326,"lo":129.316525},{"c":"m","n":"やす歯科医院","a":"奄美市名瀬港町10-4　安商事ビル１F","la":28.381406,"lo":129.494805},{"c":"m","n":"ア歯科瀬戸内診療所","a":"大島郡瀬戸内町古仁屋字大湊１０－９","la":28.148421,"lo":129.30988},{"c":"m","n":"メンタルクリニックＭａｔｅｒｉａ","a":"奄美市名瀬末広町18-25　１Ｆ","la":28.377179,"lo":129.494576},{"c":"m","n":"中村歯科・矯正歯科医院","a":"奄美市名瀬長浜町１３－７","la":28.393207,"lo":129.495},{"c":"m","n":"丸田歯科医院","a":"奄美市名瀬末広町４－６","la":28.379167,"lo":129.495908},{"c":"m","n":"住友歯科医院","a":"奄美市名瀬平松町２６５－１","la":28.398315,"lo":129.469098},{"c":"m","n":"医療法人徳洲会　瀬戸内徳洲会病院","a":"大島郡瀬戸内町古仁屋字トンキャン原1358-1","la":28.137626,"lo":129.322558},{"c":"m","n":"南大島診療所","a":"大島郡瀬戸内町阿木名字重袋1975番","la":28.148734,"lo":129.31217},{"c":"m","n":"名瀬保健所","a":"奄美市名瀬永田町１７－３","la":28.376133,"lo":129.493806},{"c":"m","n":"国民健康保険大和診療所","a":"大島郡大和村大棚大町420","la":28.355948,"lo":129.358072},{"c":"m","n":"国民健康保険宇検診療所","a":"大島郡宇検村湯湾川尻原３７","la":28.27911,"lo":129.294961},{"c":"m","n":"大和村今里へき地出張診療所","a":"大島郡大和村今里７９０","la":28.324219,"lo":129.274535},{"c":"m","n":"大和村立特別養護老人ホーム大和の園","a":"大島郡大和村戸円１９０３","la":28.347294,"lo":129.315004},{"c":"m","n":"大島保養院","a":"大島郡瀬戸内町阿木名６５","la":28.166202,"lo":129.335985},{"c":"m","n":"大島郡医師会病院","a":"奄美市名瀬小宿字苗代田３４１１","la":28.386373,"lo":129.474392},{"c":"m","n":"大野耳鼻咽喉科","a":"奄美市名瀬久里町１６－３","la":28.373521,"lo":129.497486},{"c":"m","n":"奄美の園診療所","a":"大島郡瀬戸内町古仁屋芦瀬原１２８３－２７","la":28.138232,"lo":129.32071},{"c":"m","n":"奄美中央病院","a":"奄美市名瀬長浜町１６番５号","la":28.394506,"lo":129.493505},{"c":"m","n":"奄美市住用国民健康保険診療所","a":"奄美市住用町大字西仲間１１１番地","la":28.264547,"lo":129.407499},{"c":"m","n":"奄美病院","a":"奄美市名瀬浜里町１７０番地","la":28.397167,"lo":129.471789},{"c":"m","n":"奄美眼科","a":"奄美市名瀬長浜町８番３号","la":28.391848,"lo":129.494308},{"c":"m","n":"屋宮医院","a":"奄美市名瀬久里町１８－８","la":28.373155,"lo":129.496943},{"c":"m","n":"岩城眼科","a":"奄美市名瀬末広町１－６－２Ｆ","la":28.379262,"lo":129.494602},{"c":"m","n":"嶺山内科","a":"奄美市名瀬入船町９－１５","la":28.381715,"lo":129.49302},{"c":"m","n":"政小児科内科医院","a":"奄美市名瀬柳町４－４３","la":28.379135,"lo":129.490723},{"c":"m","n":"朝仁歯科医院","a":"奄美市名瀬朝仁新町２７－１２","la":28.395402,"lo":129.485894},{"c":"m","n":"朝沼クリニック","a":"奄美市名瀬石橋町７－１","la":28.375303,"lo":129.498047},{"c":"m","n":"松岡歯科医院","a":"奄美市名瀬久里町4-6","la":28.37598,"lo":129.496782},{"c":"m","n":"柳田歯科医院","a":"奄美市名瀬石橋町９番２５号","la":28.374881,"lo":129.498248},{"c":"m","n":"歯科クリニック伊集院","a":"奄美市名瀬石橋町２０－１０","la":28.373025,"lo":129.499423},{"c":"m","n":"滝の園診療所","a":"大島郡宇検村字阿京７５７","la":28.276503,"lo":129.287115},{"c":"m","n":"瀬戸内町へき地診療所","a":"大島郡瀬戸内町古仁屋瀬久井西１３－２","la":28.144366,"lo":129.317805},{"c":"m","n":"瀬戸内町与路へき地診療所","a":"大島郡瀬戸内町与路字村内原３８４","la":28.044653,"lo":129.164407},{"c":"m","n":"瀬戸内町国民健康保険池地診療所","a":"大島郡瀬戸内町池地６６１－３","la":28.030716,"lo":129.234659},{"c":"m","n":"特別養護老人ホーム　住用の園","a":"奄美市住用町大字摺勝字俊勝袋451番３","la":28.29468,"lo":129.441345},{"c":"m","n":"特別養護老人ホーム加計呂麻園診療所","a":"大島郡瀬戸内町伊子茂１８７－１","la":28.108596,"lo":129.243878},{"c":"m","n":"登山歯科医院","a":"大島郡瀬戸内町古仁屋春日６－５","la":28.147968,"lo":129.310633},{"c":"m","n":"稲医院","a":"奄美市名瀬金久町５－４","la":28.381289,"lo":129.491731},{"c":"m","n":"美佐歯科クリニック","a":"奄美市名瀬幸町１１－１４","la":28.378868,"lo":129.492919},{"c":"m","n":"蒼Dental  Office","a":"奄美市名瀬末広町２－５アーバンビル２Ｆ","la":28.379549,"lo":129.494774},{"c":"m","n":"虹の園診療所","a":"大島郡宇検村須古２－４","la":28.271927,"lo":129.299537},{"c":"m","n":"郡山眼科医院","a":"奄美市名瀬幸町１７－３","la":28.378172,"lo":129.493437},{"c":"m","n":"障害者支援施設愛の浜園診療所","a":"奄美市名瀬大字知名瀬２５０４","la":28.381066,"lo":129.449645},{"c":"m","n":"養護老人ホームなぎさ園","a":"奄美市名瀬知名瀬字芋田口2369-13","la":28.378235,"lo":129.450422},{"c":"m","n":"養護老人ホーム寿老園","a":"大島郡瀬戸内町古仁屋瀬久井西７－３","la":28.140845,"lo":129.321213},{"c":"p","n":"奄美警察署","a":"","la":28.390771,"lo":129.495004},{"c":"p","n":"奄美警察署","a":"","la":28.390837,"lo":129.495084},{"c":"p","n":"奄美警察署住用駐在所","a":"","la":28.264744,"lo":129.40733},{"c":"p","n":"奄美警察署四谷交番","a":"","la":28.367079,"lo":129.499684},{"c":"p","n":"奄美警察署大和駐在所","a":"","la":28.357773,"lo":129.394694},{"c":"p","n":"奄美警察署小宿駐在所","a":"","la":28.399464,"lo":129.4687},{"c":"p","n":"奄美警察署屋仁川交番","a":"","la":28.380442,"lo":129.490745},{"c":"p","n":"瀬戸内警察署","a":"","la":28.138789,"lo":129.320166},{"c":"p","n":"瀬戸内警察署俵駐在所","a":"","la":28.134854,"lo":129.242226},{"c":"p","n":"瀬戸内警察署勝浦駐在所","a":"","la":28.17451,"lo":129.34958},{"c":"p","n":"瀬戸内警察署宇検駐在所","a":"","la":28.276663,"lo":129.297059},{"c":"p","n":"瀬戸内警察署桟橋交番","a":"","la":28.146826,"lo":129.309716},{"c":"p","n":"瀬戸内警察署生間駐在所","a":"","la":28.100589,"lo":129.321796},{"c":"p","n":"瀬戸内警察署篠川駐在所","a":"","la":28.221948,"lo":129.294441},{"c":"p","n":"","a":"","la":28.367089,"lo":129.499685},{"c":"s","n":"すこやか福祉センター","a":"鹿児島県瀬戸内町古仁屋船津23","la":28.146309,"lo":129.314904},{"c":"s","n":"ゼログラビティ","a":"鹿児島県瀬戸内町清水122","la":28.135807,"lo":129.328142},{"c":"s","n":"三浦集会所","a":"鹿児島県瀬戸内町三浦10","la":28.149744,"lo":129.245131},{"c":"s","n":"上役勝集会場","a":"鹿児島県奄美市住用町役勝296-25","la":28.236845,"lo":129.373241},{"c":"s","n":"下役勝集会場","a":"鹿児島県奄美市住用町役勝62","la":28.255148,"lo":129.391387},{"c":"s","n":"与路小・中学校体育館","a":"鹿児島県瀬戸内町与路484","la":28.044602,"lo":129.163649},{"c":"s","n":"与路離島住民生活センター","a":"鹿児島県瀬戸内町与路383","la":28.044443,"lo":129.164091},{"c":"s","n":"中役勝集会場","a":"鹿児島県奄美市住用町役勝190","la":28.252755,"lo":129.38146},{"c":"s","n":"久志小中学校","a":"鹿児島県宇検村久志2","la":28.286723,"lo":129.233159},{"c":"s","n":"久慈小・中学校体育館","a":"鹿児島県瀬戸内町久慈253","la":28.233082,"lo":129.253389},{"c":"s","n":"久慈集会所","a":"鹿児島県瀬戸内町久慈783","la":28.229604,"lo":129.251662},{"c":"s","n":"久根津集会所","a":"鹿児島県瀬戸内町久根津413","la":28.169945,"lo":129.297726},{"c":"s","n":"今里公民館","a":"鹿児島県大和村今里498","la":28.325341,"lo":129.27509},{"c":"s","n":"今里小学校","a":"鹿児島県大和村今里３６１－イ","la":28.326209,"lo":129.278678},{"c":"s","n":"介護老人保健施設せとうち","a":"鹿児島県瀬戸内町阿木名1975","la":28.170397,"lo":129.335833},{"c":"s","n":"伊子茂小・中学校体育館","a":"鹿児島県瀬戸内町伊子茂207","la":28.107479,"lo":129.243708},{"c":"s","n":"伊須集会所","a":"鹿児島県瀬戸内町伊須402-2","la":28.150058,"lo":129.355834},{"c":"s","n":"住用公民館","a":"鹿児島県奄美市住用町西仲間65","la":28.264586,"lo":129.407971},{"c":"s","n":"住用小学校","a":"鹿児島県奄美市住用町役勝27","la":28.254886,"lo":129.401005},{"c":"s","n":"住用町高齢者コミュニティーセンター","a":"鹿児島県奄美市住用町摺勝536-1","la":28.293803,"lo":129.443204},{"c":"s","n":"住用総合支所","a":"鹿児島県奄美市住用町大字西仲間111","la":28.265623,"lo":129.407735},{"c":"s","n":"佐念公民館","a":"鹿児島県宇検村佐念134","la":28.263074,"lo":129.236845},{"c":"s","n":"佐知克林業研修集会施設","a":"鹿児島県瀬戸内町於斉佐知克1844","la":28.088764,"lo":129.26648},{"c":"s","n":"保健センター","a":"鹿児島県奄美市名瀬井根町1-2","la":28.378124,"lo":129.490817},{"c":"s","n":"俵コミュニティーセンター","a":"鹿児島県瀬戸内町俵23","la":28.135999,"lo":129.241515},{"c":"s","n":"俵中学校体育館","a":"鹿児島県瀬戸内町俵1126","la":28.135637,"lo":129.239173},{"c":"s","n":"加計呂麻園","a":"鹿児島県瀬戸内町伊子茂187-1","la":28.108443,"lo":129.243693},{"c":"s","n":"加計呂麻島展示　体験交流館","a":"鹿児島県瀬戸内町諸鈍316","la":28.093541,"lo":129.325463},{"c":"s","n":"勝浦集会所","a":"鹿児島県瀬戸内町勝浦177","la":28.174954,"lo":129.346848},{"c":"s","n":"勝能離島住民生活センター","a":"鹿児島県瀬戸内町勝能887-2","la":28.107356,"lo":129.295327},{"c":"s","n":"古仁屋中学校体育館","a":"鹿児島県瀬戸内町古仁屋842-8","la":28.150282,"lo":129.316401},{"c":"s","n":"古仁屋小学校体育館","a":"鹿児島県瀬戸内町古仁屋805","la":28.149568,"lo":129.314169},{"c":"s","n":"古仁屋漁港ターミナルビル","a":"鹿児島県瀬戸内町古仁屋大湊26-14","la":28.145297,"lo":129.308982},{"c":"s","n":"古仁屋高等学校体育館","a":"鹿児島県瀬戸内町古仁屋399-1","la":28.151978,"lo":129.312072},{"c":"s","n":"古志集会所","a":"鹿児島県瀬戸内町古志緑1039","la":28.233233,"lo":129.276729},{"c":"s","n":"名柄公民館","a":"鹿児島県宇検村名柄1258","la":28.251762,"lo":129.249135},{"c":"s","n":"名柄小中学校","a":"鹿児島県宇検村名柄1263","la":28.252203,"lo":129.24998},{"c":"s","n":"名瀬中学校","a":"鹿児島県奄美市名瀬真名津町14-1","la":28.364574,"lo":129.498833},{"c":"s","n":"名瀬公民館金久分館","a":"鹿児島県奄美市名瀬長浜町5-1","la":28.391014,"lo":129.495006},{"c":"s","n":"名瀬小学校","a":"鹿児島県奄美市名瀬永田町1-1","la":28.376334,"lo":129.4933},{"c":"s","n":"名瀬総合支所","a":"鹿児島県奄美市名瀬幸町25-8","la":28.377662,"lo":129.493976},{"c":"s","n":"名音小学校","a":"鹿児島県大和村名音６０３－イ","la":28.334582,"lo":129.315586},{"c":"s","n":"名音生活館","a":"鹿児島県大和村名音368","la":28.335679,"lo":129.314015},{"c":"s","n":"和瀬集会場","a":"鹿児島県奄美市住用町和瀬128","la":28.295428,"lo":129.474235},{"c":"s","n":"嘉入離島住民生活センター","a":"鹿児島県瀬戸内町嘉入288","la":28.141507,"lo":129.218777},{"c":"s","n":"嘉徳集会所","a":"鹿児島県瀬戸内町嘉徳422","la":28.193453,"lo":129.403769},{"c":"s","n":"嘉鉄小学校体育館","a":"鹿児島県瀬戸内町嘉鉄353","la":28.138743,"lo":129.343986},{"c":"s","n":"嘉鉄集会所","a":"鹿児島県瀬戸内町嘉鉄322-2","la":28.138662,"lo":129.343266},{"c":"s","n":"国直公民館","a":"鹿児島県大和村国直106-2","la":28.371952,"lo":129.407018},{"c":"s","n":"城へき地福祉館","a":"鹿児島県奄美市住用町城47-1","la":28.297059,"lo":129.459809},{"c":"s","n":"大和中学校","a":"鹿児島県大和村思勝370","la":28.355704,"lo":129.39522},{"c":"s","n":"大和小学校","a":"鹿児島県大和村思勝370","la":28.355468,"lo":129.395494},{"c":"s","n":"大和小学校湯湾釜分校","a":"鹿児島県大和村湯湾釜184","la":28.364483,"lo":129.411999},{"c":"s","n":"大和村体育館","a":"鹿児島県大和村思勝485","la":28.356839,"lo":129.393506},{"c":"s","n":"大和村役場","a":"鹿児島県大和村大和浜100","la":28.358028,"lo":129.395257},{"c":"s","n":"大和村産業振興総合センター（２階多目的ホール）","a":"鹿児島県大和村大和浜100","la":28.357627,"lo":129.395269},{"c":"s","n":"大和村老人福祉センター","a":"鹿児島県大和村戸円1882-3","la":28.346846,"lo":129.315897},{"c":"s","n":"大和村防災センター","a":"鹿児島県大和村思勝477-1","la":28.356985,"lo":129.394053},{"c":"s","n":"大和村高齢者避難所","a":"鹿児島県大和村戸円452-1","la":28.350437,"lo":129.329856},{"c":"s","n":"大和浜公民館","a":"鹿児島県大和村大和浜17-29","la":28.35904,"lo":129.397209},{"c":"s","n":"大島拘置支所","a":"鹿児島県奄美市名瀬矢之脇町21-1","la":28.383969,"lo":129.491861},{"c":"s","n":"大棚公民館","a":"鹿児島県大和村大棚108-11","la":28.357224,"lo":129.359612},{"c":"s","n":"大棚小学校","a":"鹿児島県大和村大棚78-1","la":28.355833,"lo":129.359368},{"c":"s","n":"大金久防災会館","a":"鹿児島県大和村大金久312-1","la":28.361291,"lo":129.350747},{"c":"s","n":"奄美の園","a":"鹿児島県瀬戸内町古仁屋芦瀬原1283-27","la":28.13847,"lo":129.320685},{"c":"s","n":"奄美フォレストポリス","a":"鹿児島県大和村名音1476","la":28.315821,"lo":129.335959},{"c":"s","n":"奄美体験交流館","a":"鹿児島県奄美市住用町見里1084-1","la":28.290338,"lo":129.444144},{"c":"s","n":"奄美小学校","a":"鹿児島県奄美市名瀬久里町15-10","la":28.372894,"lo":129.497361},{"c":"s","n":"奄美文化センター","a":"鹿児島県奄美市名瀬長浜町517","la":28.399034,"lo":129.494905},{"c":"s","n":"奄美高校","a":"鹿児島県奄美市名瀬古田町1-1","la":28.371665,"lo":129.497988},{"c":"s","n":"宇検村地域福祉センター","a":"鹿児島県宇検村湯湾2937-87","la":28.274123,"lo":129.296127},{"c":"s","n":"宇検村生涯学習センター元気の出る館","a":"鹿児島県宇検村湯湾2937-83","la":28.275469,"lo":129.296293},{"c":"s","n":"宇検村総合体育館","a":"鹿児島県宇検村湯湾2943","la":28.276139,"lo":129.298374},{"c":"s","n":"宇検防災会館","a":"鹿児島県宇検村宇検544-2","la":28.295518,"lo":129.22919},{"c":"s","n":"安脚場集会所","a":"鹿児島県瀬戸内町度連896","la":28.107571,"lo":129.345909},{"c":"s","n":"実久集会所","a":"鹿児島県瀬戸内町実久179-2","la":28.185952,"lo":129.18546},{"c":"s","n":"寿老園","a":"鹿児島県瀬戸内町古仁屋瀬久井西7-3","la":28.144613,"lo":129.319972},{"c":"s","n":"小名瀬林業研修館","a":"鹿児島県瀬戸内町小名瀬122","la":28.196209,"lo":129.280714},{"c":"s","n":"小宿小学校","a":"鹿児島県奄美市名瀬小宿900","la":28.394454,"lo":129.464797},{"c":"s","n":"屋鈍防災会館","a":"鹿児島県宇検村58","la":28.262299,"lo":129.185483},{"c":"s","n":"山間交流施設","a":"鹿児島県奄美市住用町山間418-9","la":28.243317,"lo":129.415256},{"c":"s","n":"山間国民体育館","a":"鹿児島県奄美市住用町山間410","la":28.243569,"lo":129.416022},{"c":"s","n":"川内地区生活館","a":"鹿児島県奄美市住用町川内8","la":28.305069,"lo":129.431945},{"c":"s","n":"市営住宅生産団地集会所","a":"鹿児島県奄美市名瀬平田町16-1","la":28.360984,"lo":129.499296},{"c":"s","n":"市小中学校","a":"鹿児島県奄美市住用町市62","la":28.227712,"lo":129.453384},{"c":"s","n":"市集会場","a":"鹿児島県奄美市住用町市659","la":28.226004,"lo":129.450248},{"c":"s","n":"平松県営住宅集会場","a":"鹿児島県奄美市名瀬平松1","la":28.401001,"lo":129.469937},{"c":"s","n":"平田公民館","a":"鹿児島県宇検村平田59","la":28.253807,"lo":129.20469},{"c":"s","n":"徳浜離島住民生活センター","a":"鹿児島県瀬戸内町徳浜1170","la":28.074249,"lo":129.328587},{"c":"s","n":"志戸勘公民館","a":"鹿児島県大和村志戸勘398-3","la":28.327088,"lo":129.290627},{"c":"s","n":"思勝コミュニティセンター","a":"鹿児島県大和村思勝363-3","la":28.35505,"lo":129.395167},{"c":"s","n":"戸円公民館","a":"鹿児島県大和村戸円452-2","la":28.350706,"lo":129.329808},{"c":"s","n":"戸玉地区生活館","a":"鹿児島県奄美市住用町山間547","la":28.23617,"lo":129.42894},{"c":"s","n":"手安集会所","a":"鹿児島県瀬戸内町手安153","la":28.160946,"lo":129.297425},{"c":"s","n":"押角集会所","a":"鹿児島県瀬戸内町押角456-5","la":28.113056,"lo":129.272969},{"c":"s","n":"新川ふれあい館","a":"鹿児島県奄美市名瀬安勝町29","la":28.372466,"lo":129.499956},{"c":"s","n":"於斉高齢者コミュニティーセンター","a":"鹿児島県瀬戸内町於斉205","la":28.112424,"lo":129.249625},{"c":"s","n":"旧花天分校","a":"鹿児島県瀬戸内町花天120","la":28.22956,"lo":129.216625},{"c":"s","n":"朝仁児童館","a":"鹿児島県奄美市名瀬朝仁町22-9","la":28.398391,"lo":129.480156},{"c":"s","n":"朝仁新町集会場","a":"鹿児島県奄美市名瀬朝仁新町27-22","la":28.395373,"lo":129.486225},{"c":"s","n":"朝戸公民館","a":"鹿児島県奄美市名瀬朝戸1003","la":28.335027,"lo":129.497472},{"c":"s","n":"木慈集会所","a":"鹿児島県瀬戸内町木慈113","la":28.158565,"lo":129.220097},{"c":"s","n":"東仲間公民館","a":"鹿児島県奄美市住用町東仲間146","la":28.295253,"lo":129.434017},{"c":"s","n":"柳町集会場","a":"鹿児島県奄美市名瀬柳町20-2","la":28.380059,"lo":129.488495},{"c":"s","n":"根瀬部老人憩いの家","a":"鹿児島県奄美市名瀬根瀬部850","la":28.381095,"lo":129.432808},{"c":"s","n":"武名離島住民生活センター","a":"鹿児島県瀬戸内町武名39","la":28.153453,"lo":129.232848},{"c":"s","n":"池地小学校体育館","a":"鹿児島県瀬戸内町池地329","la":28.030108,"lo":129.238192},{"c":"s","n":"池地集会所","a":"鹿児島県瀬戸内町池地638","la":28.030729,"lo":129.232479},{"c":"s","n":"油井小・中学校体育館","a":"鹿児島県瀬戸内町油井603-1","la":28.182304,"lo":129.293379},{"c":"s","n":"油井集会所","a":"鹿児島県瀬戸内町油井602","la":28.182492,"lo":129.292964},{"c":"s","n":"津名久防災会館","a":"鹿児島県大和村津名久65-1","la":28.355284,"lo":129.400754},{"c":"s","n":"浜里団地集会場","a":"鹿児島県奄美市名瀬浜里14","la":28.399736,"lo":129.471833},{"c":"s","n":"清水公園総合　体育館","a":"鹿児島県瀬戸内町清水392","la":28.141119,"lo":129.328547},{"c":"s","n":"清水集会所","a":"鹿児島県瀬戸内町清水137","la":28.135919,"lo":129.328886},{"c":"s","n":"渡連集会所","a":"鹿児島県瀬戸内町度連227","la":28.111702,"lo":129.339579},{"c":"s","n":"湯湾会館","a":"鹿児島県宇検村湯湾712-9","la":28.278815,"lo":129.296214},{"c":"s","n":"湯湾生活館","a":"鹿児島県宇検村湯湾722","la":28.279965,"lo":129.295939},{"c":"s","n":"湯湾釜公民館","a":"鹿児島県大和村湯湾釜213","la":28.364233,"lo":129.41215},{"c":"s","n":"瀬久井集会所","a":"鹿児島県瀬戸内町古仁屋瀬久井西15-1","la":28.143761,"lo":129.318334},{"c":"s","n":"瀬戸内町きゅら島交流館","a":"鹿児島県瀬戸内町古仁屋船津33","la":28.145782,"lo":129.315245},{"c":"s","n":"瀬戸内町役場庁舎","a":"鹿児島県瀬戸内町古仁屋船津23","la":28.146519,"lo":129.314666},{"c":"s","n":"瀬武集会所","a":"鹿児島県瀬戸内町瀬武115","la":28.165899,"lo":129.209962},{"c":"s","n":"瀬相集会所","a":"鹿児島県瀬戸内町瀬相92-1","la":28.12289,"lo":129.244651},{"c":"s","n":"特別養護老人ホーム住用の園","a":"鹿児島県奄美市住用町摺勝451-3","la":28.294928,"lo":129.44174},{"c":"s","n":"特別養護老人ホーム大和の園","a":"鹿児島県大和村戸円1903","la":28.3473,"lo":129.314976},{"c":"s","n":"生勝公民館","a":"鹿児島県宇検村生勝181-2","la":28.285411,"lo":129.24348},{"c":"s","n":"生間林業研修館","a":"鹿児島県瀬戸内町生間167-1","la":28.105419,"lo":129.325362},{"c":"s","n":"田検中学校","a":"鹿児島県宇検村田検191","la":28.285865,"lo":129.290067},{"c":"s","n":"田検小学校","a":"鹿児島県宇検村田検37","la":28.285324,"lo":129.292893},{"c":"s","n":"田検防災会館","a":"鹿児島県宇検村田検296","la":28.285366,"lo":129.291996},{"c":"s","n":"知之浦集会所","a":"鹿児島県瀬戸内町武名前田原579","la":28.163232,"lo":129.263365},{"c":"s","n":"知名瀬保健福祉館","a":"鹿児島県奄美市名瀬知名瀬2317","la":28.378431,"lo":129.447747},{"c":"s","n":"石原公民館","a":"鹿児島県奄美市住用町石原168","la":28.261928,"lo":129.41232},{"c":"s","n":"石良公民館","a":"鹿児島県宇検村湯湾1640-8","la":28.269981,"lo":129.311712},{"c":"s","n":"秋徳小・中学校体育館","a":"鹿児島県瀬戸内町秋徳245","la":28.085576,"lo":129.282403},{"c":"s","n":"秋徳小中学校","a":"鹿児島県瀬戸内町秋徳245","la":28.085425,"lo":129.282833},{"c":"s","n":"秋徳離島住民生活センター","a":"鹿児島県瀬戸内町秋徳96-1","la":28.083954,"lo":129.284158},{"c":"s","n":"管鈍集会所","a":"鹿児島県瀬戸内町管鈍149-1","la":28.228112,"lo":129.194272},{"c":"s","n":"節子集会所","a":"鹿児島県瀬戸内町節子1201","la":28.166478,"lo":129.380265},{"c":"s","n":"篠川地区振興センター","a":"鹿児島県瀬戸内町篠川567-1","la":28.222393,"lo":129.294799},{"c":"s","n":"篠川小・中学校体育館","a":"鹿児島県瀬戸内町篠川150","la":28.222293,"lo":129.298552},{"c":"s","n":"網野子集会所","a":"鹿児島県瀬戸内町網野子189","la":28.169579,"lo":129.36227},{"c":"s","n":"芝集会所","a":"鹿児島県瀬戸内町芝219","la":28.192445,"lo":129.210342},{"c":"s","n":"芦検公民館","a":"鹿児島県宇検村芦検517-3","la":28.287175,"lo":129.269346},{"c":"s","n":"花富集会所","a":"鹿児島県瀬戸内町花富117","la":28.100102,"lo":129.239451},{"c":"s","n":"薩川中学校体育館","a":"鹿児島県瀬戸内町薩川150","la":28.178638,"lo":129.204444},{"c":"s","n":"薩川小学校講堂","a":"鹿児島県瀬戸内町薩川211","la":28.180115,"lo":129.202729},{"c":"s","n":"薩川集会所","a":"鹿児島県瀬戸内町薩川189","la":28.180469,"lo":129.202257},{"c":"s","n":"蘇刈集会所","a":"鹿児島県瀬戸内町蘇刈447","la":28.135818,"lo":129.359949},{"c":"s","n":"西仲間公民館","a":"鹿児島県奄美市住用町西仲間309","la":28.26673,"lo":129.409081},{"c":"s","n":"西古見防災コミュニティセンター","a":"鹿児島県瀬戸内町西古見603-1","la":28.240876,"lo":129.171415},{"c":"s","n":"西阿室小学校","a":"鹿児島県瀬戸内町西阿室135","la":28.111738,"lo":129.222101},{"c":"s","n":"西阿室小学校体育館","a":"鹿児島県瀬戸内町西阿室135","la":28.111559,"lo":129.222299},{"c":"s","n":"西阿室離島住民生活センター","a":"鹿児島県瀬戸内町西阿室146-5","la":28.111275,"lo":129.22238},{"c":"s","n":"見里公民館","a":"鹿児島県奄美市住用町見里17","la":28.288338,"lo":129.440901},{"c":"s","n":"請阿室集会所","a":"鹿児島県瀬戸内町請阿室401-1","la":28.028547,"lo":129.254162},{"c":"s","n":"諸数集会所","a":"鹿児島県瀬戸内町諸数252-1","la":28.107926,"lo":129.314491},{"c":"s","n":"諸鈍小・中学校体育館","a":"鹿児島県瀬戸内町諸鈍371","la":28.094596,"lo":129.326098},{"c":"s","n":"諸鈍離島住民生活センター","a":"鹿児島県瀬戸内町諸鈍295","la":28.091454,"lo":129.326103},{"c":"s","n":"谷村サロン","a":"鹿児島県奄美市名瀬井根町16-20","la":28.375867,"lo":129.491111},{"c":"s","n":"部連公民館","a":"鹿児島県宇検村部連622-7","la":28.260943,"lo":129.273688},{"c":"s","n":"里公民館","a":"鹿児島県奄美市名瀬小宿字里1693","la":28.386158,"lo":129.466293},{"c":"s","n":"野見山青少年研修センター","a":"鹿児島県瀬戸内町野見山361","la":28.094189,"lo":129.29123},{"c":"s","n":"金久中学校","a":"鹿児島県奄美市名瀬塩浜町15-10","la":28.388095,"lo":129.492894},{"c":"s","n":"長浜町集会場","a":"鹿児島県奄美市名瀬長浜町26-8","la":28.396181,"lo":129.494878},{"c":"s","n":"阿多地集会所","a":"鹿児島県瀬戸内町阿多地96","la":28.152098,"lo":129.1987},{"c":"s","n":"阿室いこいの家","a":"鹿児島県宇検村阿室6655","la":28.255408,"lo":129.20108},{"c":"s","n":"阿室小中学校","a":"鹿児島県宇検村阿室195","la":28.256631,"lo":129.200229},{"c":"s","n":"阿室釜林業研修館","a":"鹿児島県瀬戸内町阿室釜4-13","la":28.220525,"lo":129.294727},{"c":"s","n":"阿室防災会館","a":"鹿児島県宇検村阿室89","la":28.255554,"lo":129.20078},{"c":"s","n":"阿木名小・中学校体育館","a":"鹿児島県瀬戸内町阿木名2141","la":28.17074,"lo":129.337676},{"c":"s","n":"阿木名集会所","a":"鹿児島県瀬戸内町阿木名17","la":28.167,"lo":129.334104},{"c":"s","n":"阿鉄集会所","a":"鹿児島県瀬戸内町阿鉄725","la":28.189575,"lo":129.290605},{"c":"s","n":"須古公民館","a":"鹿児島県宇検村須古472-5","la":28.272245,"lo":129.293942},{"c":"s","n":"須子茂集会所","a":"鹿児島県瀬戸内町須子茂62","la":28.146254,"lo":129.210956},{"c":"s","n":"須手集会所","a":"鹿児島県瀬戸内町手安785-5","la":28.151145,"lo":129.300329},{"c":"s","n":"養護老人ホームなぎさ園","a":"鹿児島県奄美市名瀬知名瀬2369-13","la":28.379796,"lo":129.45016},{"c":"s","n":"高丘集会所","a":"鹿児島県瀬戸内町古仁屋233-3","la":28.155324,"lo":129.31301},{"c":"s","n":"ＡｉＡｉひろば","a":"鹿児島県奄美市名瀬末広町14-10","la":28.377491,"lo":129.495858}]