[{"c":"f","n":"고성소방서","a":"","la":34.980978,"lo":128.330729},{"c":"f","n":"무전119 안전센터","a":"통영시원문로71","la":34.859257,"lo":128.420829},{"c":"f","n":"사천소방서","a":"사천시남일로29","la":34.933223,"lo":128.079798},{"c":"f","n":"사천소방서 구조대","a":"사천시진삼로212","la":34.975713,"lo":128.062451},{"c":"f","n":"삼동의용소방대","a":"","la":34.829671,"lo":128.006102},{"c":"f","n":"죽림119","a":"","la":34.883345,"lo":128.419134},{"c":"f","n":"통영소방서","a":"","la":34.883543,"lo":128.419086},{"c":"p","n":"경남 고성경찰서","a":"고성군중앙로113","la":34.97586,"lo":128.332299},{"c":"p","n":"경남 사천경찰서","a":"사천시남일로37","la":34.933162,"lo":128.080806},{"c":"p","n":"경남 통영경찰서","a":"통영시죽림3로53","la":34.882976,"lo":128.419727},{"c":"p","n":"고성경찰서 거류파출소","a":"고성군거류로655","la":34.989539,"lo":128.404505},{"c":"p","n":"고성경찰서 공룡지구대","a":"고성군대가로27","la":34.983967,"lo":128.318416},{"c":"p","n":"고성경찰서 상리파출소","a":"고성군척번정1길98","la":34.999462,"lo":128.186925},{"c":"p","n":"고성경찰서 하이파출소","a":"고성군남일로433","la":34.928596,"lo":128.122491},{"c":"p","n":"교통민원관","a":"","la":34.93288,"lo":128.080892},{"c":"p","n":"남해경찰서 미조파출소","a":"남해군미송로52","la":34.712307,"lo":128.045626},{"c":"p","n":"남해경찰서 삼동파출소","a":"남해군동부대로1876번길8","la":34.831425,"lo":128.000375},{"c":"p","n":"남해경찰서 창선파출소","a":"남해군창선로99","la":34.857867,"lo":128.012505},{"c":"p","n":"남해파출소","a":"","la":34.708213,"lo":128.045686},{"c":"p","n":"대교치안센터","a":"거제시거제대로6232","la":34.887392,"lo":128.488142},{"c":"p","n":"사천경찰서 남양파출소","a":"사천시진삼로122","la":34.968132,"lo":128.064608},{"c":"p","n":"사천경찰서 삼천포지구대","a":"사천시중앙로89","la":34.934249,"lo":128.07684},{"c":"p","n":"창선출장소","a":"남해군동부대로2964번길39","la":34.917315,"lo":128.032338},{"c":"p","n":"통영경찰서 광도지구대","a":"통영시죽림3로25","la":34.883079,"lo":128.416354},{"c":"p","n":"통영경찰서 미수지구대","a":"통영시운하2길17","la":34.832393,"lo":128.411882},{"c":"p","n":"통영경찰서 민원실","a":"","la":34.882559,"lo":128.419262},{"c":"p","n":"통영경찰서 북신지구대","a":"통영시무전대로40","la":34.859807,"lo":128.42503},{"c":"p","n":"통영경찰서 사량파출소","a":"통영시진촌2길17","la":34.844509,"lo":128.225073},{"c":"p","n":"통영경찰서 산양파출소","a":"통영시산양중앙로1","la":34.801367,"lo":128.388265},{"c":"p","n":"통영경찰서 욕지파출소","a":"통영시천왕로29","la":34.636282,"lo":128.26472},{"c":"p","n":"통영경찰서 중앙지구대","a":"통영시중앙로170","la":34.840519,"lo":128.423353},{"c":"p","n":"통영해양경찰서","a":"","la":34.839971,"lo":128.418351},{"c":"p","n":"통영해양경찰서 삼동출장소","a":"","la":34.79387,"lo":128.051998},{"c":"p","n":"통영해양경찰서 포교출장소","a":"","la":34.904048,"lo":128.275264},{"c":"p","n":"하일치안센터","a":"","la":34.942156,"lo":128.197993},{"c":"p","n":"","a":"","la":34.926464,"lo":128.079543},{"c":"p","n":"","a":"고성군두포1길163-9","la":34.904052,"lo":128.275263},{"c":"p","n":"","a":"남해군창선로99","la":34.85787,"lo":128.012508}]