[{"c":"f","n":"광산소방서","a":"","la":35.184893,"lo":126.834757},{"c":"f","n":"광주광역시 소방안전본부","a":"광주광역시내방로 광주광역시청111","la":35.159958,"lo":126.852358},{"c":"f","n":"광주서부소방서","a":"광주광역시화운로197","la":35.156526,"lo":126.876533},{"c":"f","n":"금호119안전센터","a":"운천로112","la":35.142698,"lo":126.85827},{"c":"f","n":"나주119안전센터","a":"","la":35.027854,"lo":126.709946},{"c":"f","n":"남부소방서 송하119안전센터","a":"송암로58번길13","la":35.110543,"lo":126.878379},{"c":"f","n":"남평 119안전센터","a":"","la":35.041464,"lo":126.846042},{"c":"f","n":"담양소방서","a":"","la":35.318178,"lo":126.97311},{"c":"f","n":"대산119안전센터","a":"공음대산로932","la":35.339949,"lo":126.598343},{"c":"f","n":"동림119안전센터","a":"","la":35.186452,"lo":126.870284},{"c":"f","n":"동부소방서","a":"광주광역시제봉로210","la":35.154571,"lo":126.914809},{"c":"f","n":"동화119지역대","a":"수연로23","la":35.284483,"lo":126.738746},{"c":"f","n":"북부소방서","a":"","la":35.186543,"lo":126.912216},{"c":"f","n":"북이면의용소방대","a":"","la":35.429144,"lo":126.809744},{"c":"f","n":"비아119안전센터","a":"비아로12번길10","la":35.220764,"lo":126.82359},{"c":"f","n":"상무119안전센터","a":"치평로65","la":35.153279,"lo":126.84715},{"c":"f","n":"성송면의용소방대","a":"대성로770-2","la":35.364248,"lo":126.646212},{"c":"f","n":"소방시설고장신고센터","a":"송암로24번길56","la":35.110533,"lo":126.884849},{"c":"f","n":"송정119안전센터","a":"광주광역시","la":35.129178,"lo":126.785539},{"c":"f","n":"용면의용소방대","a":"추월산로358","la":35.363832,"lo":126.987268},{"c":"f","n":"월산119안전센터","a":"광주광역시수박등로1","la":35.140594,"lo":126.894612},{"c":"f","n":"일곡119안전센터","a":"","la":35.206313,"lo":126.897341},{"c":"f","n":"임동119안전센터","a":"","la":35.168887,"lo":126.890699},{"c":"f","n":"장성119안전센터 소방서","a":"단풍로204","la":35.320283,"lo":126.800062},{"c":"f","n":"지산119안전센터","a":"","la":35.149964,"lo":126.938675},{"c":"f","n":"첨단 119 안전센터 / 특수구조단","a":"","la":35.218477,"lo":126.849107},{"c":"f","n":"풍암119안전센터","a":"","la":35.123689,"lo":126.862686},{"c":"f","n":"함평소방서","a":"","la":35.060199,"lo":126.539466},{"c":"f","n":"화순소방서","a":"","la":35.050736,"lo":126.9714},{"c":"f","n":"","a":"나주시그린로296","la":35.013139,"lo":126.79608},{"c":"f","n":"","a":"","la":35.137553,"lo":126.810224},{"c":"f","n":"","a":"단풍로","la":35.320308,"lo":126.799641},{"c":"p","n":"고창경찰서 공음파출소","a":"공음길39-1","la":35.378231,"lo":126.512374},{"c":"p","n":"고창경찰서 대산파출소","a":"고산성로4","la":35.33921,"lo":126.600794},{"c":"p","n":"고창경찰서 모양지구대","a":"","la":35.427456,"lo":126.69539},{"c":"p","n":"고창경찰서 무장파출소","a":"","la":35.416631,"lo":126.561943},{"c":"p","n":"고창경찰서 성송파출소","a":"대성로777","la":35.365025,"lo":126.645964},{"c":"p","n":"고창경찰서 아산파출소","a":"","la":35.439918,"lo":126.635832},{"c":"p","n":"고창경찰서 해리파출소","a":"","la":35.456916,"lo":126.541897},{"c":"p","n":"광산경찰서","a":"광주광역시","la":35.152768,"lo":126.782707},{"c":"p","n":"광산경찰서 수완지구대","a":"광주광역시수완로63","la":35.190912,"lo":126.828483},{"c":"p","n":"광주 경찰특공대","a":"광주광역시","la":35.134342,"lo":126.673538},{"c":"p","n":"광주남부경찰서","a":"","la":35.122835,"lo":126.92053},{"c":"p","n":"광주남부경찰서 양림파출소","a":"천변좌로410","la":35.142973,"lo":126.915225},{"c":"p","n":"광주동부경찰서","a":"","la":35.1492,"lo":126.919851},{"c":"p","n":"광주북부경찰서","a":"","la":35.186643,"lo":126.898992},{"c":"p","n":"광주북부경찰서 동운지구대","a":"","la":35.187131,"lo":126.866149},{"c":"p","n":"광주서부경찰서","a":"상무공원로71","la":35.150809,"lo":126.842011},{"c":"p","n":"광주서부경찰서","a":"상무공원로71","la":35.151142,"lo":126.842712},{"c":"p","n":"광주서부경찰서 화정지구대","a":"광주광역시화운로160","la":35.153141,"lo":126.876881},{"c":"p","n":"광주서부청소년경찰학교","a":"광주광역시죽봉대로118","la":35.163869,"lo":126.884017},{"c":"p","n":"광주지방경찰청","a":"광주광역시용아로112","la":35.153831,"lo":126.800427},{"c":"p","n":"광주지방경찰청 제1기동대","a":"","la":35.123102,"lo":126.921278},{"c":"p","n":"금호지구대","a":"","la":35.135298,"lo":126.859417},{"c":"p","n":"나주경찰서","a":"나주시영산로5415-22","la":35.038646,"lo":126.721023},{"c":"p","n":"나주경찰서 금성지구대","a":"나주시학생운동길16","la":35.02813,"lo":126.721306},{"c":"p","n":"나주경찰서 금천파출소","a":"나주시금영로941","la":35.031564,"lo":126.753516},{"c":"p","n":"나주경찰서 남평파출소","a":"나주시남평1로37","la":35.047375,"lo":126.841675},{"c":"p","n":"나주경찰서 노안파출소","a":"나주시금산로32-53","la":35.076821,"lo":126.732823},{"c":"p","n":"나주경찰서 다시파출소","a":"나주시다시로185","la":35.017575,"lo":126.637744},{"c":"p","n":"나주경찰서 산포파출소","a":"나주시산포로443-5","la":35.037251,"lo":126.801561},{"c":"p","n":"다시파출소","a":"","la":35.0176,"lo":126.637774},{"c":"p","n":"담양경찰서 고서파출소","a":"담양군가사문학로320","la":35.223348,"lo":126.972769},{"c":"p","n":"담양경찰서 대전파출소","a":"담양군대전로4","la":35.276787,"lo":126.888343},{"c":"p","n":"담양경찰서 수북파출소","a":"담양군추성1로715","la":35.302062,"lo":126.929777},{"c":"p","n":"도산파출소","a":"광주광역시","la":35.129029,"lo":126.785479},{"c":"p","n":"동천파출소","a":"","la":35.170981,"lo":126.864391},{"c":"p","n":"동천파출소","a":"","la":35.164177,"lo":126.859502},{"c":"p","n":"묘량치안센터","a":"묘량로245-16","la":35.253283,"lo":126.542139},{"c":"p","n":"문평치안센터","a":"","la":35.05561,"lo":126.603739},{"c":"p","n":"문흥 지구대","a":"대천로146","la":35.187014,"lo":126.921517},{"c":"p","n":"방범소","a":"","la":35.111987,"lo":126.895973},{"c":"p","n":"본량파출소","a":"","la":35.181474,"lo":126.730441},{"c":"p","n":"북상치안센터","a":"장성군백양로608","la":35.41225,"lo":126.851095},{"c":"p","n":"불갑치안센터","a":"함영로2902","la":35.212323,"lo":126.506655},{"c":"p","n":"비아파출소","a":"광주광역시","la":35.221645,"lo":126.823871},{"c":"p","n":"빛가람파출소","a":"나주시그린로310","la":35.013973,"lo":126.796082},{"c":"p","n":"상무지구대","a":"","la":35.157772,"lo":126.850467},{"c":"p","n":"서삼치안센터","a":"장성군축령로349","la":35.33217,"lo":126.766929},{"c":"p","n":"송월주공방범초소","a":"","la":35.02701,"lo":126.713812},{"c":"p","n":"순창경찰서 복흥파출소","a":"","la":35.431375,"lo":126.930732},{"c":"p","n":"영광경찰서 대마파출소","a":"영광군영장로253","la":35.301473,"lo":126.578733},{"c":"p","n":"영광경찰서 읍내지구대","a":"영광군천년로13길29","la":35.275612,"lo":126.506538},{"c":"p","n":"용면치안센터","a":"추령로1","la":35.363997,"lo":126.986685},{"c":"p","n":"우산 지구대","a":"","la":35.1783,"lo":126.919907},{"c":"p","n":"유덕치안센터","a":"천변우하로309-26","la":35.1665,"lo":126.85484},{"c":"p","n":"일곡 지구대","a":"","la":35.203024,"lo":126.898167},{"c":"p","n":"장성경찰서 북이파출소","a":"장성군갈재로3","la":35.430903,"lo":126.810159},{"c":"p","n":"장성경찰서 북일파출소","a":"장성군신흥로410","la":35.375455,"lo":126.806895},{"c":"p","n":"장성경찰서 북하파출소","a":"장성군백양로896","la":35.407482,"lo":126.882019},{"c":"p","n":"장성경찰서 삼계파출소","a":"장성군사창로58","la":35.259103,"lo":126.665633},{"c":"p","n":"장성경찰서 삼서파출소","a":"장성군해삼로1163","la":35.234973,"lo":126.647198},{"c":"p","n":"장성경찰서 읍내파출소","a":"장성군역전로80","la":35.299261,"lo":126.78064},{"c":"p","n":"장성경찰서 진남파출소","a":"장성군못재로93","la":35.245442,"lo":126.812027},{"c":"p","n":"전남 담양경찰서","a":"담양군무정로15","la":35.309813,"lo":126.982982},{"c":"p","n":"전남 영광경찰서","a":"","la":35.277822,"lo":126.512422},{"c":"p","n":"전남 장성경찰서","a":"장성군영천로164","la":35.299739,"lo":126.782322},{"c":"p","n":"전남 함평경찰서","a":"함평군중앙길220","la":35.065374,"lo":126.51546},{"c":"p","n":"전남 화순경찰서","a":"화순군자치샘로29","la":35.062433,"lo":126.984856},{"c":"p","n":"전남담양경찰서 중앙파출소","a":"담양군중앙로73","la":35.319709,"lo":126.982437},{"c":"p","n":"전북 고창경찰서","a":"고창군보릿골로175","la":35.441401,"lo":126.695162},{"c":"p","n":"진원치안센터","a":"장성군노사로509","la":35.272595,"lo":126.83441},{"c":"p","n":"첨단지구대","a":"광주광역시","la":35.216317,"lo":126.846542},{"c":"p","n":"충장치안센터","a":"충장로64","la":35.14935,"lo":126.914579},{"c":"p","n":"풍암파출소","a":"","la":35.124379,"lo":126.878795},{"c":"p","n":"학서파출소","a":"양림로119번길13","la":35.140863,"lo":126.919922},{"c":"p","n":"함평경찰서 나산파출소","a":"함평군나산길84","la":35.113056,"lo":126.609745},{"c":"p","n":"함평경찰서 남부파출소","a":"함평군닻빼기길2","la":35.016492,"lo":126.537847},{"c":"p","n":"함평경찰서 대동파출소","a":"함평군대동길5-8","la":35.068452,"lo":126.531175},{"c":"p","n":"함평경찰서 월야파출소","a":"함평군밀재로1551","la":35.179077,"lo":126.631856},{"c":"p","n":"함평경찰서 읍내파출소","a":"함평군함장로1202-16","la":35.05836,"lo":126.526517},{"c":"p","n":"함평경찰서 해보파출소","a":"함평군밀재로1255","la":35.182097,"lo":126.601127},{"c":"p","n":"화순경찰서 역전파출소","a":"화순군오성로488","la":35.052117,"lo":126.961914},{"c":"p","n":"화순경찰서 읍내지구대","a":"화순군충의로152","la":35.054475,"lo":126.99301},{"c":"p","n":"효덕파출소","a":"","la":35.112086,"lo":126.899757},{"c":"p","n":"","a":"","la":35.187355,"lo":126.899564},{"c":"p","n":"","a":"광주광역시","la":35.181481,"lo":126.730427},{"c":"p","n":"","a":"","la":35.186641,"lo":126.898974},{"c":"p","n":"","a":"","la":35.186659,"lo":126.898922},{"c":"p","n":"","a":"나주시금영로941","la":35.031553,"lo":126.75343},{"c":"p","n":"","a":"나주시금영로941","la":35.031567,"lo":126.753536}]