[{"c":"e","n":"あ・りーさだの杜","a":"北海道夕張市沼ノ沢35","la":42.954917,"lo":142.030715},{"c":"e","n":"とみかわ児童館","a":"北海道日高町富川北2-8-1","la":42.521857,"lo":142.033131},{"c":"e","n":"とみかわ老人憩の家","a":"北海道日高町富川北2-8-2","la":42.521435,"lo":142.033448},{"c":"e","n":"ふれあいセンターびらとり","a":"北海道平取町本町35-1","la":42.585657,"lo":142.134429},{"c":"e","n":"ふれあい広場","a":"北海道日高町富川北2-214","la":42.520914,"lo":142.032391},{"c":"e","n":"ゆうばり小学校","a":"北海道夕張市清水沢清陵町14","la":42.98893,"lo":142.013753},{"c":"e","n":"ペナコリ生活館","a":"北海道平取町字荷負33-1","la":42.66469,"lo":142.184021},{"c":"e","n":"三和生活館","a":"北海道日高町字三和82-173","la":42.593501,"lo":142.351828},{"c":"e","n":"二風谷生活館","a":"北海道平取町字二風谷78-12","la":42.636398,"lo":142.161517},{"c":"e","n":"仁和会館","a":"北海道むかわ町穂別仁和339","la":42.660697,"lo":142.080027},{"c":"e","n":"佐留太生活館","a":"北海道日高町富川東4-4-24","la":42.508381,"lo":142.035356},{"c":"e","n":"北海道富川高等学校","a":"北海道日高町富川西12-69-109","la":42.511233,"lo":142.011672},{"c":"e","n":"夕張中学校","a":"北海道夕張市南清水沢3-63","la":42.982858,"lo":142.000117},{"c":"e","n":"夕張市農業研修センター","a":"北海道夕張市沼ノ沢827-4","la":42.955458,"lo":142.027966},{"c":"e","n":"夕張紅葉園","a":"北海道夕張市紅葉山178","la":42.936149,"lo":142.04254},{"c":"e","n":"夕張高等学校","a":"北海道夕張市南清水沢3-49","la":42.980447,"lo":142.005236},{"c":"e","n":"太陽地区高台（大槻地先）","a":"北海道新冠町字太陽14-2","la":42.522336,"lo":142.373235},{"c":"e","n":"太陽地区高台（高橋地先）","a":"北海道新冠町字太陽289-1","la":42.527934,"lo":142.396492},{"c":"e","n":"富仁家会館","a":"北海道日高町富川東5-178-4","la":42.501683,"lo":142.034309},{"c":"e","n":"富内銀河会館","a":"北海道むかわ町穂別富内81-15","la":42.784128,"lo":142.22006},{"c":"e","n":"富岡生活館","a":"北海道日高町字富岡284-8","la":42.854763,"lo":142.439049},{"c":"e","n":"富川中学校","a":"北海道日高町富川北7-3-6","la":42.525588,"lo":142.037411},{"c":"e","n":"富川多目的グラウンド","a":"北海道日高町富川東1-706-4","la":42.513894,"lo":142.036355},{"c":"e","n":"富川小学校","a":"北海道日高町富川東1-1-1","la":42.513922,"lo":142.034407},{"c":"e","n":"富川平松会館","a":"北海道日高町富川西8-1047-6","la":42.5299,"lo":142.001463},{"c":"e","n":"富川母と子の家","a":"北海道日高町富川南5-4-1","la":42.513906,"lo":142.017758},{"c":"e","n":"富川生活館","a":"北海道日高町富川西1-1-1","la":42.521522,"lo":142.023936},{"c":"e","n":"富川自動車学校","a":"北海道日高町富川西1-5-4","la":42.522171,"lo":142.019628},{"c":"e","n":"富川複合施設","a":"北海道日高町富川北3-3-16","la":42.520948,"lo":142.029375},{"c":"e","n":"富川防災ステーション","a":"北海道日高町富川東2-950-2","la":42.505009,"lo":142.042595},{"c":"e","n":"小平生活館","a":"北海道平取町字小平3-6","la":42.598265,"lo":142.148879},{"c":"e","n":"岩知志ふれあい館","a":"北海道平取町字岩知志55-9","la":42.733803,"lo":142.347842},{"c":"e","n":"川向生活館","a":"北海道平取町字川向61-3","la":42.541979,"lo":142.109148},{"c":"e","n":"幌毛志生活改善センター","a":"北海道平取町字幌毛志49-1","la":42.717964,"lo":142.262399},{"c":"e","n":"平取小学校","a":"北海道平取町本町105-6","la":42.586623,"lo":142.125654},{"c":"e","n":"平賀生活館","a":"北海道日高町字平賀312-1","la":42.530385,"lo":142.046042},{"c":"e","n":"幾千世生活館","a":"北海道日高町字幾千世166-2","la":42.500119,"lo":142.11484},{"c":"e","n":"広富山村研修センター","a":"北海道日高町字広富96-1","la":42.575848,"lo":142.215317},{"c":"e","n":"広富生活館","a":"北海道日高町字広富96-1","la":42.575872,"lo":142.215237},{"c":"e","n":"庫富コミュニティーセンター","a":"北海道日高町字庫富282","la":42.528853,"lo":142.152497},{"c":"e","n":"庫富生活館","a":"北海道日高町字庫富278-2","la":42.526788,"lo":142.152289},{"c":"e","n":"振内町民センター","a":"北海道平取町振内町28-11","la":42.726102,"lo":142.302224},{"c":"e","n":"新光町生活館","a":"北海道日高町富川北2-10-2","la":42.52229,"lo":142.032747},{"c":"e","n":"新和地区高台（錦岡牧場地先）","a":"北海道新冠町字新和262","la":42.538494,"lo":142.346216},{"c":"e","n":"新栄団地集会所","a":"北海道日高町富川北7-5-7","la":42.526381,"lo":142.03415},{"c":"e","n":"日高こもれびホール","a":"北海道日高町宮下町1-411-1","la":42.880396,"lo":142.43737},{"c":"e","n":"日高小学校","a":"北海道日高町松風町2-254-1","la":42.880488,"lo":142.445092},{"c":"e","n":"日高町民センター","a":"北海道日高町松風町1-116-2","la":42.878045,"lo":142.448193},{"c":"e","n":"日高老人福祉センター","a":"北海道日高町本町東1-297-4","la":42.878304,"lo":142.442502},{"c":"e","n":"日高西部消防組合消防署庁舎屋上","a":"北海道日高町富川北7-1-10","la":42.523382,"lo":142.03783},{"c":"e","n":"日高高等学校（体育館）","a":"北海道日高町松風町1-124-1","la":42.879415,"lo":142.449255},{"c":"e","n":"旧仁和小学校体育館","a":"北海道むかわ町穂別仁和344","la":42.661305,"lo":142.0769},{"c":"e","n":"旧清陵町さわやかホール","a":"北海道夕張市清水沢清陵町62-7","la":42.984107,"lo":142.016028},{"c":"e","n":"旧荷負小学校","a":"北海道平取町字荷負77-3","la":42.678767,"lo":142.202314},{"c":"e","n":"旭生活館","a":"北海道平取町字旭67-3","la":42.645142,"lo":142.373016},{"c":"e","n":"旭町生活館","a":"北海道日高町富川南6-12-4","la":42.512456,"lo":142.014417},{"c":"e","n":"本村生活館","a":"北海道平取町字貫気別20-2","la":42.665207,"lo":142.236238},{"c":"e","n":"本町東会館","a":"北海道日高町本町東2-111-34","la":42.87696,"lo":142.445088},{"c":"e","n":"正和地域交流センター","a":"北海道日高町字正和195-23","la":42.550481,"lo":142.329507},{"c":"e","n":"池売生活センター","a":"北海道平取町振内町90-8","la":42.723118,"lo":142.297252},{"c":"e","n":"沙流川歴史館","a":"北海道平取町字二風谷227-2","la":42.637308,"lo":142.155912},{"c":"e","n":"河原団地集会所","a":"北海道日高町富川南3-4-13","la":42.51695,"lo":142.024173},{"c":"e","n":"町営富川球場","a":"北海道日高町富川南2-69-3","la":42.518894,"lo":142.020456},{"c":"e","n":"町営日高球場","a":"北海道日高町本町東2-261-3","la":42.878504,"lo":142.443712},{"c":"e","n":"稲里生活館","a":"北海道むかわ町穂別稲里243-2","la":42.849097,"lo":142.170372},{"c":"e","n":"紫雲古津小学校","a":"北海道平取町字紫雲古津38-5","la":42.556064,"lo":142.075187},{"c":"e","n":"総合体育館・武道館","a":"北海道日高町松風町1-116-2","la":42.878673,"lo":142.448455},{"c":"e","n":"緑ケ丘生活館","a":"北海道日高町字緑町167-2","la":42.510746,"lo":142.08736},{"c":"e","n":"美宇地区高台（ノースヒルズ地先）","a":"北海道新冠町字美宇207","la":42.507664,"lo":142.367263},{"c":"e","n":"美宇地区高台（益子地先）","a":"北海道新冠町字美宇155-7","la":42.516203,"lo":142.409846},{"c":"e","n":"芽生ふれあいセンター","a":"北海道平取町字芽生39-1","la":42.672292,"lo":142.356019},{"c":"e","n":"豊糠改善センター","a":"北海道平取町字豊糠24-3","la":42.705765,"lo":142.40455},{"c":"e","n":"豊郷生活館","a":"北海道日高町字豊郷447-5","la":42.507408,"lo":142.179087},{"c":"e","n":"貫気別生活館","a":"北海道平取町字貫気別129-2","la":42.670798,"lo":142.261534},{"c":"e","n":"里平地区高台（佐藤地先）","a":"北海道新冠町字里平70-4","la":42.555799,"lo":142.417531},{"c":"e","n":"長知内ふれあいセンター","a":"北海道平取町字長知内38-5","la":42.703114,"lo":142.229471},{"c":"f","n":"夕張市消防本部","a":"","la":42.995021,"lo":142.009059},{"c":"f","n":"日高西部消防組合 消防本部","a":"日高町10","la":42.523634,"lo":142.038026},{"c":"f","n":"日高西部消防組合消防署","a":"平取町1","la":42.58521,"lo":142.130552},{"c":"f","n":"日高西部消防組合消防署","a":"日高町2","la":42.878215,"lo":142.438899},{"c":"f","n":"日高西部消防組合消防署","a":"平取町11","la":42.726007,"lo":142.301694},{"c":"f","n":"胆振東部消防組合消防署","a":"むかわ町5","la":42.764378,"lo":142.135488},{"c":"f","n":"","a":"","la":42.982326,"lo":142.39969},{"c":"m","n":"ほべつ歯科クリニック","a":"勇払郡むかわ町穂別81番地1号","la":42.766051,"lo":142.138388},{"c":"m","n":"むかわ町国民健康保険穂別診療所","a":"勇払郡むかわ町穂別81番地8","la":42.76638,"lo":142.138074},{"c":"m","n":"やなづめファミリー歯科","a":"夕張市南清水沢3丁目27番地１","la":42.981856,"lo":142.005296},{"c":"m","n":"メイプル歯科トミカワ","a":"日高町富川北4丁目2番10号","la":42.520642,"lo":142.026505},{"c":"m","n":"医療法人社団　中條医院","a":"夕張市紅葉山526-40","la":42.937218,"lo":142.038809},{"c":"m","n":"医療法人社団ぬまた歯科","a":"日高町富川北2丁目6番4号","la":42.520537,"lo":142.033809},{"c":"m","n":"医療法人社団小川医院","a":"日高町富川西2丁目5番3号","la":42.524594,"lo":142.019038},{"c":"m","n":"医療法人社団桜和会みんなの歯科クリニック","a":"平取町本町18番地3","la":42.583845,"lo":142.126862},{"c":"m","n":"南清水沢診療所","a":"夕張市南清水沢4丁目8番地6","la":42.983879,"lo":142.008516},{"c":"m","n":"占冠きむら歯科","a":"勇払郡占冠村字中央","la":42.959073,"lo":142.39161},{"c":"m","n":"占冠村歯科診療所","a":"勇払郡占冠村字シムカプ原野57番5","la":42.978879,"lo":142.402926},{"c":"m","n":"土井歯科医院","a":"日高町富川北6丁目2番42号","la":42.523107,"lo":142.037656},{"c":"m","n":"富川グロリアクリニック","a":"日高町富川南4丁目2番47号","la":42.517093,"lo":142.022738},{"c":"m","n":"平取歯科診療所","a":"平取町本町67番地1","la":42.5883,"lo":142.136921},{"c":"m","n":"平取町国民健康保険病院","a":"沙流郡平取町本町67番地1","la":42.589067,"lo":142.137081},{"c":"m","n":"平取町振内歯科診療所","a":"平取町振内28番地7","la":42.725474,"lo":142.301156},{"c":"m","n":"平取町振内診療所","a":"平取町振内町28番地8","la":42.725634,"lo":142.301117},{"c":"m","n":"平取町貫気別歯科診療所","a":"平取町貫気別129番地5","la":42.670779,"lo":142.262116},{"c":"m","n":"日高町立富川国民健康保険診療所","a":"日高町富川北6丁目3番26号","la":42.522965,"lo":142.03582},{"c":"m","n":"日高町立日高国民健康保険診療所","a":"沙流郡日高町栄町東1丁目303番地の2","la":42.879069,"lo":142.441227},{"c":"m","n":"日高町立日高歯科診療所","a":"日高町栄町東1丁目303の15","la":42.878615,"lo":142.440464},{"c":"m","n":"日高町立特別養護老人ホーム日高高寿園医務室","a":"日高町栄町東1丁目303番地の12","la":42.879026,"lo":142.440222},{"c":"m","n":"村立占冠診療所","a":"勇払郡占冠村字中央","la":42.979587,"lo":142.397746},{"c":"m","n":"清水沢歯科医院","a":"夕張市清水沢3丁目3","la":42.999232,"lo":142.007427},{"c":"m","n":"特別養護老人ホーム平取かつら園医務室","a":"平取町本町17番地1","la":42.583845,"lo":142.126207},{"c":"m","n":"特別養護老人ホーム愛誠園医務室","a":"勇払郡むかわ町穂別80番地10","la":42.766408,"lo":142.136951},{"c":"m","n":"社会福祉法人　清光園医務室","a":"夕張市南清水沢1丁目55番1","la":42.986899,"lo":142.001753},{"c":"m","n":"簗詰医院","a":"夕張市清水沢3丁目65","la":42.996816,"lo":142.008386},{"c":"m","n":"鎌田歯科医院","a":"日高町富川南2丁目2番28号","la":42.518396,"lo":142.023444},{"c":"m","n":"養護老人ホーム　夕張紅葉園診療所","a":"夕張市紅葉山178番地","la":42.936199,"lo":142.042553},{"c":"p","n":"栗山警察署　紅葉山駐在所","a":"","la":42.936266,"lo":142.038922},{"c":"p","n":"栗山警察署沼の沢駐在所","a":"","la":42.955844,"lo":142.032437},{"c":"p","n":"苫小牧警察署 穂別駐在所","a":"むかわ町26","la":42.763569,"lo":142.137307},{"c":"p","n":"門別警察署","a":"日高町1","la":42.512157,"lo":142.035504},{"c":"p","n":"門別警察署 富川交番","a":"日高町5","la":42.519753,"lo":142.027333},{"c":"p","n":"門別警察署 平取駐在所","a":"平取町1","la":42.584275,"lo":142.127569},{"c":"p","n":"門別警察署 振内駐在所","a":"平取町10","la":42.726173,"lo":142.301424},{"c":"p","n":"門別警察署 日高駐在所","a":"日高町15","la":42.881527,"lo":142.435708},{"c":"p","n":"門別警察署 荷負駐在所","a":"平取町6","la":42.679629,"lo":142.197757},{"c":"p","n":"","a":"","la":42.978462,"lo":142.40203},{"c":"s","n":"あ・りーさだの杜","a":"北海道夕張市沼ノ沢35","la":42.956191,"lo":142.03098},{"c":"s","n":"さくら認定こども園","a":"北海道むかわ町穂別80-1","la":42.766023,"lo":142.136292},{"c":"s","n":"ふれあいセンターびらとり","a":"北海道平取町本町35-1","la":42.585606,"lo":142.134435},{"c":"s","n":"みどりが丘住民センター","a":"北海道平取町本町114-5","la":42.587033,"lo":142.130339},{"c":"s","n":"ゆうばり小学校","a":"北海道夕張市清水沢清陵町14","la":42.98893,"lo":142.013753},{"c":"s","n":"ペナコリ生活館","a":"北海道平取町字荷負33-1","la":42.664749,"lo":142.183967},{"c":"s","n":"三和生活館","a":"北海道日高町字三和82-173","la":42.593501,"lo":142.351828},{"c":"s","n":"中央公民館","a":"北海道平取町本町88-1","la":42.589089,"lo":142.13705},{"c":"s","n":"二風谷小学校","a":"北海道平取町字二風谷28-1","la":42.631749,"lo":142.15389},{"c":"s","n":"仁和下生活館","a":"北海道むかわ町穂別仁和199-4","la":42.648129,"lo":142.079128},{"c":"s","n":"仁和会館","a":"北海道むかわ町穂別仁和339","la":42.660708,"lo":142.080016},{"c":"s","n":"佐留太生活館","a":"北海道日高町富川東4-4-24","la":42.508381,"lo":142.035357},{"c":"s","n":"北海道富川高等学校","a":"北海道日高町富川西12-69-109","la":42.511233,"lo":142.011672},{"c":"s","n":"占冠中学校","a":"北海道占冠村字中央","la":42.980315,"lo":142.402347},{"c":"s","n":"占冠村コミュニティプラザ","a":"北海道占冠村字中央","la":42.97832,"lo":142.397754},{"c":"s","n":"占冠村保健福祉センター「ノンノ」","a":"北海道占冠村字中央","la":42.97909,"lo":142.394182},{"c":"s","n":"占冠村総合センター","a":"北海道占冠村字中央","la":42.979872,"lo":142.398527},{"c":"s","n":"去場生活館","a":"北海道平取町字去場66-4","la":42.5601,"lo":142.09532},{"c":"s","n":"双民館","a":"北海道占冠村字双珠別","la":42.947819,"lo":142.442138},{"c":"s","n":"双珠別住民センター","a":"北海道占冠村字双珠別","la":42.952125,"lo":142.437741},{"c":"s","n":"和泉上生活館","a":"北海道むかわ町穂別和泉226-16","la":42.727575,"lo":142.131763},{"c":"s","n":"国立日高青少年自然の家","a":"北海道日高町字富岡","la":42.874081,"lo":142.451408},{"c":"s","n":"夕張中学校","a":"北海道夕張市南清水沢3-63","la":42.982858,"lo":142.000117},{"c":"s","n":"夕張市農業研修センター","a":"北海道夕張市沼ノ沢827-4","la":42.955458,"lo":142.027966},{"c":"s","n":"夕張紅葉園","a":"北海道夕張市紅葉山178","la":42.936149,"lo":142.04254},{"c":"s","n":"夕張高等学校","a":"北海道夕張市南清水沢3-49","la":42.980447,"lo":142.005236},{"c":"s","n":"太陽開拓婦人ホーム","a":"北海道新冠町字太陽204-16","la":42.526329,"lo":142.412961},{"c":"s","n":"安住生活館","a":"北海道むかわ町穂別安住72-2","la":42.783851,"lo":142.23345},{"c":"s","n":"富内銀河会館","a":"北海道むかわ町穂別富内81-15","la":42.784122,"lo":142.22006},{"c":"s","n":"富川中学校","a":"北海道日高町富川北7-3-6","la":42.525588,"lo":142.037411},{"c":"s","n":"富川小学校","a":"北海道日高町富川東1-1-1","la":42.513922,"lo":142.034407},{"c":"s","n":"富川生活館","a":"北海道日高町富川西1-1-1","la":42.521498,"lo":142.02383},{"c":"s","n":"富川複合施設","a":"北海道日高町富川北3-3-16","la":42.520927,"lo":142.028702},{"c":"s","n":"富川防災ステーション","a":"北海道日高町富川東2-950-2","la":42.505009,"lo":142.042595},{"c":"s","n":"小平生活館","a":"北海道平取町字小平3-6","la":42.59828,"lo":142.1489},{"c":"s","n":"岩知志ふれあい館","a":"北海道平取町字岩知志55-9","la":42.733795,"lo":142.347848},{"c":"s","n":"川向生活館","a":"北海道平取町川向61-3","la":42.541983,"lo":142.109145},{"c":"s","n":"川東第２集落センター","a":"北海道むかわ町生田441-3","la":42.59466,"lo":142.058191},{"c":"s","n":"幌毛志生活改善センター","a":"北海道平取町字幌毛志49-1","la":42.717971,"lo":142.262371},{"c":"s","n":"平取中学校","a":"北海道平取町本町116-3","la":42.589293,"lo":142.121327},{"c":"s","n":"平取生活館","a":"北海道平取町本町19","la":42.584396,"lo":142.126814},{"c":"s","n":"平賀生活館","a":"北海道日高町字平賀312-1","la":42.530385,"lo":142.046042},{"c":"s","n":"幾千世生活館","a":"北海道日高町字幾千世166-2","la":42.500127,"lo":142.114837},{"c":"s","n":"広富山村研修センター","a":"北海道日高町字広富96-1","la":42.575848,"lo":142.215317},{"c":"s","n":"広富生活館","a":"北海道日高町字広富96-1","la":42.575872,"lo":142.215237},{"c":"s","n":"庫富コミュニティーセンター","a":"北海道日高町字庫富282","la":42.528853,"lo":142.152497},{"c":"s","n":"庫富生活館","a":"北海道日高町字庫富278-2","la":42.526788,"lo":142.152289},{"c":"s","n":"振内中学校","a":"北海道平取町振内町101-1","la":42.722469,"lo":142.300807},{"c":"s","n":"振内小学校","a":"北海道平取町振内町30-2","la":42.72518,"lo":142.303641},{"c":"s","n":"振内町民センター","a":"北海道平取町振内町28-11","la":42.726045,"lo":142.30204},{"c":"s","n":"振内青少年会館","a":"北海道平取町振内町28-11","la":42.72572,"lo":142.30215},{"c":"s","n":"振内１４町内集会所","a":"北海道平取町振内町49-10","la":42.732601,"lo":142.296873},{"c":"s","n":"新光町生活館","a":"北海道日高町富川北2-10-2","la":42.52229,"lo":142.032747},{"c":"s","n":"新和生活館","a":"北海道新冠町字新和143-3","la":42.542702,"lo":142.334501},{"c":"s","n":"日高こもれびホール","a":"北海道日高町宮下町1-411-1","la":42.880396,"lo":142.43737},{"c":"s","n":"日高町民センター","a":"北海道日高町松風町1-116-2","la":42.878045,"lo":142.448193},{"c":"s","n":"日高高等学校（体育館）","a":"北海道日高町松風町1-124-1","la":42.879415,"lo":142.449255},{"c":"s","n":"旧仁和小学校","a":"北海道むかわ町穂別仁和344","la":42.661202,"lo":142.077517},{"c":"s","n":"旧富内小学校","a":"北海道むかわ町穂別富内91-3","la":42.788563,"lo":142.222576},{"c":"s","n":"旭岡生活館","a":"北海道むかわ町旭岡58-3","la":42.607058,"lo":142.07734},{"c":"s","n":"旭生活館","a":"北海道平取町字旭67-3","la":42.645161,"lo":142.37308},{"c":"s","n":"旭町生活館","a":"北海道日高町富川南6-12-4","la":42.512456,"lo":142.014417},{"c":"s","n":"有明集会所","a":"北海道むかわ町有明38-1","la":42.613738,"lo":142.091039},{"c":"s","n":"本村生活館","a":"北海道平取町字貫気別20-2","la":42.665227,"lo":142.236228},{"c":"s","n":"本町生活館","a":"北海道平取町本町44-4","la":42.586722,"lo":142.137092},{"c":"s","n":"栄生活館","a":"北海道むかわ町穂別栄71-7","la":42.659655,"lo":142.066201},{"c":"s","n":"正和地域交流センター","a":"北海道日高町字正和195-23","la":42.550481,"lo":142.329507},{"c":"s","n":"池売生活センター","a":"北海道平取町振内町90-8","la":42.723128,"lo":142.297078},{"c":"s","n":"泉地区避難所（大森地先）","a":"北海道新冠町字泉247-5","la":42.501782,"lo":142.463088},{"c":"s","n":"特別養護老人ホーム日高高寿園","a":"北海道日高町栄町東1-303-12","la":42.87896,"lo":142.440197},{"c":"s","n":"稲里生活館","a":"北海道むかわ町穂別稲里243-2","la":42.849093,"lo":142.170397},{"c":"s","n":"穂別ふれあい健康センター","a":"北海道むかわ町穂別81","la":42.766474,"lo":142.138731},{"c":"s","n":"穂別スポーツセンター","a":"北海道むかわ町穂別449-4","la":42.753053,"lo":142.137489},{"c":"s","n":"穂別中央生活館","a":"北海道むかわ町穂別和泉76-1","la":42.706527,"lo":142.127394},{"c":"s","n":"穂別中学校","a":"北海道むかわ町穂別116","la":42.769316,"lo":142.142304},{"c":"s","n":"穂別小学校","a":"北海道むかわ町穂別114-2","la":42.769864,"lo":142.139605},{"c":"s","n":"穂別町民センター","a":"北海道むかわ町穂別2-1","la":42.761251,"lo":142.133803},{"c":"s","n":"穂別高等学校","a":"北海道むかわ町穂別127","la":42.770986,"lo":142.139954},{"c":"s","n":"紫雲古津生活館","a":"北海道平取町紫雲古津34-1","la":42.550876,"lo":142.070997},{"c":"s","n":"総合体育館・武道館","a":"北海道日高町松風町1-116-2","la":42.878673,"lo":142.448455},{"c":"s","n":"緑ケ丘生活館","a":"北海道日高町字緑町167-2","la":42.510746,"lo":142.08736},{"c":"s","n":"美園地区集会所","a":"北海道占冠村字中央","la":42.990083,"lo":142.400226},{"c":"s","n":"美宇生活センター","a":"北海道新冠町字美宇299-2","la":42.501371,"lo":142.350551},{"c":"s","n":"芽呂生活改善センター","a":"北海道新冠町字美宇179-9","la":42.502877,"lo":142.385141},{"c":"s","n":"芽生生活改善センター","a":"北海道平取町字芽生39-1","la":42.672288,"lo":142.356009},{"c":"s","n":"荷菜多目的研修センター","a":"北海道平取町字荷菜73-9","la":42.574805,"lo":142.112238},{"c":"s","n":"荷負生活館","a":"北海道平取町字荷負54-2","la":42.67948,"lo":142.197318},{"c":"s","n":"豊田生活館","a":"北海道むかわ町穂別豊田294-3","la":42.713807,"lo":142.115263},{"c":"s","n":"豊糠体験宿泊施設「とよぬか山荘」","a":"北海道平取町字豊糠24-3","la":42.70586,"lo":142.40533},{"c":"s","n":"豊郷生活館","a":"北海道日高町字豊郷447-5","la":42.507408,"lo":142.179087},{"c":"s","n":"貫気別小学校","a":"北海道平取町字貫気別91-6","la":42.675989,"lo":142.264637},{"c":"s","n":"貫気別町民センター","a":"北海道平取町字貫気別129","la":42.670818,"lo":142.261121},{"c":"s","n":"貫気別福祉センター","a":"北海道平取町字貫気別135-9","la":42.673692,"lo":142.2643},{"c":"s","n":"里平生活センター","a":"北海道新冠町字里平20-3","la":42.554436,"lo":142.398381},{"c":"s","n":"長知内ふれあいセンター","a":"北海道平取町字長知内38-5","la":42.703128,"lo":142.229529}]